{
    "Kabul": "{\"CO\": {\"concentration\": 767.71, \"aqi\": 8}, \"NO2\": {\"concentration\": 4.97, \"aqi\": 6}, \"O3\": {\"concentration\": 128.75, \"aqi\": 205}, \"SO2\": {\"concentration\": 0.54, \"aqi\": 0}, \"PM2.5\": {\"concentration\": 13.94, \"aqi\": 45}, \"PM10\": {\"concentration\": 26.29, \"aqi\": 24}, \"overall_aqi\": 205}",
    "Tirana": "{\"CO\": {\"concentration\": 216.96, \"aqi\": 2}, \"NO2\": {\"concentration\": 6.34, \"aqi\": 7}, \"O3\": {\"concentration\": 87.98, \"aqi\": 132}, \"SO2\": {\"concentration\": 0.67, \"aqi\": 0}, \"PM2.5\": {\"concentration\": 57.54, \"aqi\": 134}, \"PM10\": {\"concentration\": 70.27, \"aqi\": 58}, \"overall_aqi\": 134}",
    "Alger": "{\"CO\": {\"concentration\": 230.31, \"aqi\": 2}, \"NO2\": {\"concentration\": 4.07, \"aqi\": 5}, \"O3\": {\"concentration\": 131.61, \"aqi\": 206}, \"SO2\": {\"concentration\": 1.58, \"aqi\": 2}, \"PM2.5\": {\"concentration\": 6.85, \"aqi\": 22}, \"PM10\": {\"concentration\": 12.3, \"aqi\": 11}, \"overall_aqi\": 206}",
    "Fagatogo": "{\"CO\": {\"concentration\": 213.62, \"aqi\": 2}, \"NO2\": {\"concentration\": 0.06, \"aqi\": 0}, \"O3\": {\"concentration\": 72.24, \"aqi\": 91}, \"SO2\": {\"concentration\": 0.36, \"aqi\": 0}, \"PM2.5\": {\"concentration\": 6.97, \"aqi\": 22}, \"PM10\": {\"concentration\": 13.73, \"aqi\": 12}, \"overall_aqi\": 91}",
    "Andorra la Vella": "{\"CO\": {\"concentration\": 158.55, \"aqi\": 1}, \"NO2\": {\"concentration\": 0.32, \"aqi\": 0}, \"O3\": {\"concentration\": 70.81, \"aqi\": 86}, \"SO2\": {\"concentration\": 0.07, \"aqi\": 0}, \"PM2.5\": {\"concentration\": 0.91, \"aqi\": 2}, \"PM10\": {\"concentration\": 1.28, \"aqi\": 1}, \"overall_aqi\": 86}",
    "Luanda": "{\"CO\": {\"concentration\": 654.22, \"aqi\": 7}, \"NO2\": {\"concentration\": 6.17, \"aqi\": 7}, \"O3\": {\"concentration\": 68.67, \"aqi\": 80}, \"SO2\": {\"concentration\": 2.38, \"aqi\": 3}, \"PM2.5\": {\"concentration\": 14.97, \"aqi\": 48}, \"PM10\": {\"concentration\": 36.78, \"aqi\": 34}, \"overall_aqi\": 80}",
    "The Valley": "{\"CO\": {\"concentration\": 236.99, \"aqi\": 2}, \"NO2\": {\"concentration\": 0.06, \"aqi\": 0}, \"O3\": {\"concentration\": 24.68, \"aqi\": 20}, \"SO2\": {\"concentration\": 0.14, \"aqi\": 0}, \"PM2.5\": {\"concentration\": 1.4, \"aqi\": 4}, \"PM10\": {\"concentration\": 4.2, \"aqi\": 3}, \"overall_aqi\": 20}",
    "Saint John's": "{\"CO\": {\"concentration\": 188.59, \"aqi\": 2}, \"NO2\": {\"concentration\": 1.25, \"aqi\": 1}, \"O3\": {\"concentration\": 52.21, \"aqi\": 44}, \"SO2\": {\"concentration\": 1.43, \"aqi\": 2}, \"PM2.5\": {\"concentration\": 2.41, \"aqi\": 7}, \"PM10\": {\"concentration\": 5.53, \"aqi\": 5}, \"overall_aqi\": 44}",
    "Buenos Aires": "{\"CO\": {\"concentration\": 580.79, \"aqi\": 6}, \"NO2\": {\"concentration\": 29.13, \"aqi\": 36}, \"O3\": {\"concentration\": 4.78, \"aqi\": 4}, \"SO2\": {\"concentration\": 22.89, \"aqi\": 33}, \"PM2.5\": {\"concentration\": 14.03, \"aqi\": 45}, \"PM10\": {\"concentration\": 24.64, \"aqi\": 22}, \"overall_aqi\": 45}",
    "Yerevan": "{\"CO\": {\"concentration\": 203.61, \"aqi\": 2}, \"NO2\": {\"concentration\": 4.46, \"aqi\": 5}, \"O3\": {\"concentration\": 121.59, \"aqi\": 202}, \"SO2\": {\"concentration\": 1.51, \"aqi\": 2}, \"PM2.5\": {\"concentration\": 7.92, \"aqi\": 25}, \"PM10\": {\"concentration\": 13.96, \"aqi\": 12}, \"overall_aqi\": 202}",
    "Oranjestad": "{\"CO\": {\"concentration\": 230.31, \"aqi\": 2}, \"NO2\": {\"concentration\": 0.63, \"aqi\": 0}, \"O3\": {\"concentration\": 47.92, \"aqi\": 40}, \"SO2\": {\"concentration\": 1, \"aqi\": 1}, \"PM2.5\": {\"concentration\": 3.81, \"aqi\": 12}, \"PM10\": {\"concentration\": 11.41, \"aqi\": 10}, \"overall_aqi\": 40}",
    "Canberra": "{\"CO\": {\"concentration\": 223.64, \"aqi\": 2}, \"NO2\": {\"concentration\": 3.64, \"aqi\": 4}, \"O3\": {\"concentration\": 42.92, \"aqi\": 36}, \"SO2\": {\"concentration\": 0.92, \"aqi\": 1}, \"PM2.5\": {\"concentration\": 2.2, \"aqi\": 7}, \"PM10\": {\"concentration\": 3.24, \"aqi\": 3}, \"overall_aqi\": 36}",
    "Wien": "{\"CO\": {\"concentration\": 236.99, \"aqi\": 2}, \"NO2\": {\"concentration\": 4.67, \"aqi\": 5}, \"O3\": {\"concentration\": 90.84, \"aqi\": 139}, \"SO2\": {\"concentration\": 2.71, \"aqi\": 3}, \"PM2.5\": {\"concentration\": 2.58, \"aqi\": 8}, \"PM10\": {\"concentration\": 3.13, \"aqi\": 2}, \"overall_aqi\": 139}",
    "Baku": "{\"CO\": {\"concentration\": 257.02, \"aqi\": 2}, \"NO2\": {\"concentration\": 19.88, \"aqi\": 24}, \"O3\": {\"concentration\": 54.36, \"aqi\": 46}, \"SO2\": {\"concentration\": 1.12, \"aqi\": 1}, \"PM2.5\": {\"concentration\": 7.03, \"aqi\": 22}, \"PM10\": {\"concentration\": 29.09, \"aqi\": 26}, \"overall_aqi\": 46}",
    "Nassau": "{\"CO\": {\"concentration\": 233.65, \"aqi\": 2}, \"NO2\": {\"concentration\": 4.28, \"aqi\": 5}, \"O3\": {\"concentration\": 43.99, \"aqi\": 37}, \"SO2\": {\"concentration\": 6.5, \"aqi\": 9}, \"PM2.5\": {\"concentration\": 1.69, \"aqi\": 5}, \"PM10\": {\"concentration\": 3.17, \"aqi\": 2}, \"overall_aqi\": 37}",
    "al-Manama": "{\"CO\": {\"concentration\": 250.34, \"aqi\": 2}, \"NO2\": {\"concentration\": 3, \"aqi\": 3}, \"O3\": {\"concentration\": 164.51, \"aqi\": 219}, \"SO2\": {\"concentration\": 9.66, \"aqi\": 14}, \"PM2.5\": {\"concentration\": 41.12, \"aqi\": 101}, \"PM10\": {\"concentration\": 89.72, \"aqi\": 67}, \"overall_aqi\": 219}",
    "Dhaka": "{\"CO\": {\"concentration\": 433.92, \"aqi\": 4}, \"NO2\": {\"concentration\": 9.51, \"aqi\": 11}, \"O3\": {\"concentration\": 22.89, \"aqi\": 19}, \"SO2\": {\"concentration\": 3.52, \"aqi\": 5}, \"PM2.5\": {\"concentration\": 8.21, \"aqi\": 26}, \"PM10\": {\"concentration\": 15.82, \"aqi\": 14}, \"overall_aqi\": 26}",
    "Bridgetown": "{\"CO\": {\"concentration\": 216.96, \"aqi\": 2}, \"NO2\": {\"concentration\": 3.09, \"aqi\": 3}, \"O3\": {\"concentration\": 40.41, \"aqi\": 34}, \"SO2\": {\"concentration\": 3.73, \"aqi\": 5}, \"PM2.5\": {\"concentration\": 2.48, \"aqi\": 8}, \"PM10\": {\"concentration\": 3.6, \"aqi\": 3}, \"overall_aqi\": 34}",
    "Minsk": "{\"CO\": {\"concentration\": 257.02, \"aqi\": 2}, \"NO2\": {\"concentration\": 6.26, \"aqi\": 7}, \"O3\": {\"concentration\": 101.57, \"aqi\": 166}, \"SO2\": {\"concentration\": 4.71, \"aqi\": 6}, \"PM2.5\": {\"concentration\": 15.18, \"aqi\": 49}, \"PM10\": {\"concentration\": 16.07, \"aqi\": 14}, \"overall_aqi\": 166}",
    "Bruxelles [Brussel]": "{\"CO\": {\"concentration\": 267.03, \"aqi\": 3}, \"NO2\": {\"concentration\": 18.51, \"aqi\": 23}, \"O3\": {\"concentration\": 25.75, \"aqi\": 21}, \"SO2\": {\"concentration\": 1.8, \"aqi\": 2}, \"PM2.5\": {\"concentration\": 2.88, \"aqi\": 9}, \"PM10\": {\"concentration\": 3.49, \"aqi\": 3}, \"overall_aqi\": 23}",
    "Belmopan": "{\"CO\": {\"concentration\": 156.88, \"aqi\": 1}, \"NO2\": {\"concentration\": 0.13, \"aqi\": 0}, \"O3\": {\"concentration\": 9.48, \"aqi\": 8}, \"SO2\": {\"concentration\": 0.13, \"aqi\": 0}, \"PM2.5\": {\"concentration\": 2.38, \"aqi\": 7}, \"PM10\": {\"concentration\": 2.74, \"aqi\": 2}, \"overall_aqi\": 8}",
    "Porto-Novo": "{\"CO\": {\"concentration\": 527.38, \"aqi\": 5}, \"NO2\": {\"concentration\": 2.01, \"aqi\": 2}, \"O3\": {\"concentration\": 30.04, \"aqi\": 25}, \"SO2\": {\"concentration\": 1.49, \"aqi\": 2}, \"PM2.5\": {\"concentration\": 4.23, \"aqi\": 13}, \"PM10\": {\"concentration\": 7.28, \"aqi\": 6}, \"overall_aqi\": 25}",
    "Hamilton": "{\"CO\": {\"concentration\": 467.3, \"aqi\": 5}, \"NO2\": {\"concentration\": 33.59, \"aqi\": 41}, \"O3\": {\"concentration\": 45.78, \"aqi\": 38}, \"SO2\": {\"concentration\": 8.35, \"aqi\": 12}, \"PM2.5\": {\"concentration\": 10.22, \"aqi\": 33}, \"PM10\": {\"concentration\": 13.88, \"aqi\": 12}, \"overall_aqi\": 41}",
    "Thimphu": "{\"CO\": {\"concentration\": 343.8, \"aqi\": 3}, \"NO2\": {\"concentration\": 1.8, \"aqi\": 2}, \"O3\": {\"concentration\": 29.33, \"aqi\": 24}, \"SO2\": {\"concentration\": 1.7, \"aqi\": 2}, \"PM2.5\": {\"concentration\": 8.3, \"aqi\": 26}, \"PM10\": {\"concentration\": 11.56, \"aqi\": 10}, \"overall_aqi\": 26}",
    "La Paz": "{\"CO\": {\"concentration\": 467.3, \"aqi\": 5}, \"NO2\": {\"concentration\": 1.27, \"aqi\": 1}, \"O3\": {\"concentration\": 111.58, \"aqi\": 191}, \"SO2\": {\"concentration\": 3.31, \"aqi\": 4}, \"PM2.5\": {\"concentration\": 14.03, \"aqi\": 45}, \"PM10\": {\"concentration\": 17.97, \"aqi\": 16}, \"overall_aqi\": 191}",
    "Sarajevo": "{\"CO\": {\"concentration\": 205.28, \"aqi\": 2}, \"NO2\": {\"concentration\": 1.65, \"aqi\": 2}, \"O3\": {\"concentration\": 82.97, \"aqi\": 119}, \"SO2\": {\"concentration\": 7.09, \"aqi\": 10}, \"PM2.5\": {\"concentration\": 9.24, \"aqi\": 30}, \"PM10\": {\"concentration\": 11.6, \"aqi\": 10}, \"overall_aqi\": 119}",
    "Gaborone": "{\"CO\": {\"concentration\": 453.95, \"aqi\": 5}, \"NO2\": {\"concentration\": 3.13, \"aqi\": 3}, \"O3\": {\"concentration\": 170.23, \"aqi\": 221}, \"SO2\": {\"concentration\": 0.89, \"aqi\": 1}, \"PM2.5\": {\"concentration\": 28.84, \"aqi\": 76}, \"PM10\": {\"concentration\": 39.18, \"aqi\": 36}, \"overall_aqi\": 221}",
    "Bras\u00edlia": "{\"CO\": {\"concentration\": 230.31, \"aqi\": 2}, \"NO2\": {\"concentration\": 0.78, \"aqi\": 0}, \"O3\": {\"concentration\": 77.96, \"aqi\": 107}, \"SO2\": {\"concentration\": 1.22, \"aqi\": 1}, \"PM2.5\": {\"concentration\": 3.61, \"aqi\": 11}, \"PM10\": {\"concentration\": 5.16, \"aqi\": 4}, \"overall_aqi\": 107}",
    "Bandar Seri Begawan": "{\"CO\": {\"concentration\": 347.14, \"aqi\": 3}, \"NO2\": {\"concentration\": 4.2, \"aqi\": 5}, \"O3\": {\"concentration\": 11.27, \"aqi\": 9}, \"SO2\": {\"concentration\": 1.28, \"aqi\": 1}, \"PM2.5\": {\"concentration\": 3.53, \"aqi\": 11}, \"PM10\": {\"concentration\": 3.63, \"aqi\": 3}, \"overall_aqi\": 11}",
    "Sofia": "{\"CO\": {\"concentration\": 240.33, \"aqi\": 2}, \"NO2\": {\"concentration\": 4.16, \"aqi\": 5}, \"O3\": {\"concentration\": 94.41, \"aqi\": 148}, \"SO2\": {\"concentration\": 2.09, \"aqi\": 3}, \"PM2.5\": {\"concentration\": 9.81, \"aqi\": 31}, \"PM10\": {\"concentration\": 11.99, \"aqi\": 11}, \"overall_aqi\": 148}",
    "Ouagadougou": "{\"CO\": {\"concentration\": 507.36, \"aqi\": 5}, \"NO2\": {\"concentration\": 2.04, \"aqi\": 2}, \"O3\": {\"concentration\": 33.26, \"aqi\": 28}, \"SO2\": {\"concentration\": 1.79, \"aqi\": 2}, \"PM2.5\": {\"concentration\": 7.14, \"aqi\": 23}, \"PM10\": {\"concentration\": 14.27, \"aqi\": 13}, \"overall_aqi\": 28}",
    "Bujumbura": "{\"CO\": {\"concentration\": 574.11, \"aqi\": 6}, \"NO2\": {\"concentration\": 3.43, \"aqi\": 4}, \"O3\": {\"concentration\": 28.61, \"aqi\": 24}, \"SO2\": {\"concentration\": 1.42, \"aqi\": 2}, \"PM2.5\": {\"concentration\": 10.68, \"aqi\": 34}, \"PM10\": {\"concentration\": 25.38, \"aqi\": 23}, \"overall_aqi\": 34}",
    "Phnom Penh": "{\"CO\": {\"concentration\": 2082.82, \"aqi\": 23}, \"NO2\": {\"concentration\": 18.17, \"aqi\": 22}, \"O3\": {\"concentration\": 17.88, \"aqi\": 15}, \"SO2\": {\"concentration\": 6.86, \"aqi\": 10}, \"PM2.5\": {\"concentration\": 58.78, \"aqi\": 136}, \"PM10\": {\"concentration\": 70.42, \"aqi\": 58}, \"overall_aqi\": 136}",
    "Yaounde": "{\"CO\": {\"concentration\": 390.53, \"aqi\": 4}, \"NO2\": {\"concentration\": 0.56, \"aqi\": 0}, \"O3\": {\"concentration\": 18.77, \"aqi\": 15}, \"SO2\": {\"concentration\": 0.34, \"aqi\": 0}, \"PM2.5\": {\"concentration\": 1.52, \"aqi\": 4}, \"PM10\": {\"concentration\": 2.62, \"aqi\": 2}, \"overall_aqi\": 15}",
    "Ottawa": "{\"CO\": {\"concentration\": 178.58, \"aqi\": 2}, \"NO2\": {\"concentration\": 1.37, \"aqi\": 1}, \"O3\": {\"concentration\": 20.39, \"aqi\": 17}, \"SO2\": {\"concentration\": 0.24, \"aqi\": 0}, \"PM2.5\": {\"concentration\": 0.83, \"aqi\": 2}, \"PM10\": {\"concentration\": 1.23, \"aqi\": 1}, \"overall_aqi\": 17}",
    "Praia": "{\"CO\": {\"concentration\": 223.64, \"aqi\": 2}, \"NO2\": {\"concentration\": 0.46, \"aqi\": 0}, \"O3\": {\"concentration\": 46.49, \"aqi\": 39}, \"SO2\": {\"concentration\": 0.21, \"aqi\": 0}, \"PM2.5\": {\"concentration\": 6.21, \"aqi\": 20}, \"PM10\": {\"concentration\": 7.44, \"aqi\": 6}, \"overall_aqi\": 39}",
    "George Town": "{\"CO\": {\"concentration\": 290.39, \"aqi\": 3}, \"NO2\": {\"concentration\": 0.39, \"aqi\": 0}, \"O3\": {\"concentration\": 30.04, \"aqi\": 25}, \"SO2\": {\"concentration\": 0.07, \"aqi\": 0}, \"PM2.5\": {\"concentration\": 0.64, \"aqi\": 2}, \"PM10\": {\"concentration\": 0.91, \"aqi\": 0}, \"overall_aqi\": 25}",
    "Bangui": "{\"CO\": {\"concentration\": 330.45, \"aqi\": 3}, \"NO2\": {\"concentration\": 0.03, \"aqi\": 0}, \"O3\": {\"concentration\": 2.68, \"aqi\": 2}, \"SO2\": {\"concentration\": 0.02, \"aqi\": 0}, \"PM2.5\": {\"concentration\": 0.5, \"aqi\": 1}, \"PM10\": {\"concentration\": 0.64, \"aqi\": 0}, \"overall_aqi\": 3}",
    "N'Djamena": "{\"CO\": {\"concentration\": 377.18, \"aqi\": 4}, \"NO2\": {\"concentration\": 0.71, \"aqi\": 0}, \"O3\": {\"concentration\": 24.32, \"aqi\": 20}, \"SO2\": {\"concentration\": 0.59, \"aqi\": 0}, \"PM2.5\": {\"concentration\": 10.43, \"aqi\": 33}, \"PM10\": {\"concentration\": 57.81, \"aqi\": 51}, \"overall_aqi\": 51}",
    "Santiago de Chile": "{\"CO\": {\"concentration\": 4486.08, \"aqi\": 50}, \"NO2\": {\"concentration\": 67.17, \"aqi\": 83}, \"O3\": {\"concentration\": 143.05, \"aqi\": 210}, \"SO2\": {\"concentration\": 28.37, \"aqi\": 41}, \"PM2.5\": {\"concentration\": 444.35, \"aqi\": 500}, \"PM10\": {\"concentration\": 517.33, \"aqi\": 500}, \"overall_aqi\": 500}",
    "Peking": "{\"CO\": {\"concentration\": 1922.61, \"aqi\": 21}, \"NO2\": {\"concentration\": 61.69, \"aqi\": 77}, \"O3\": {\"concentration\": 0, \"aqi\": 0}, \"SO2\": {\"concentration\": 66.76, \"aqi\": 64}, \"PM2.5\": {\"concentration\": 228.07, \"aqi\": 277}, \"PM10\": {\"concentration\": 298.89, \"aqi\": 172}, \"overall_aqi\": 277}",
    "Flying Fish Cove": "{\"CO\": {\"concentration\": 303.75, \"aqi\": 3}, \"NO2\": {\"concentration\": 0.14, \"aqi\": 0}, \"O3\": {\"concentration\": 50.07, \"aqi\": 42}, \"SO2\": {\"concentration\": 0.31, \"aqi\": 0}, \"PM2.5\": {\"concentration\": 16.19, \"aqi\": 51}, \"PM10\": {\"concentration\": 27.78, \"aqi\": 25}, \"overall_aqi\": 51}",
    "West Island": "{\"CO\": {\"concentration\": 287.06, \"aqi\": 3}, \"NO2\": {\"concentration\": 0.07, \"aqi\": 0}, \"O3\": {\"concentration\": 75.82, \"aqi\": 102}, \"SO2\": {\"concentration\": 0.26, \"aqi\": 0}, \"PM2.5\": {\"concentration\": 4.08, \"aqi\": 13}, \"PM10\": {\"concentration\": 12.46, \"aqi\": 11}, \"overall_aqi\": 102}",
    "Moroni": "{\"CO\": {\"concentration\": 263.69, \"aqi\": 2}, \"NO2\": {\"concentration\": 0.85, \"aqi\": 1}, \"O3\": {\"concentration\": 50.78, \"aqi\": 43}, \"SO2\": {\"concentration\": 0.44, \"aqi\": 0}, \"PM2.5\": {\"concentration\": 5.17, \"aqi\": 16}, \"PM10\": {\"concentration\": 12.38, \"aqi\": 11}, \"overall_aqi\": 43}",
    "Brazzaville": "{\"CO\": {\"concentration\": 574.11, \"aqi\": 6}, \"NO2\": {\"concentration\": 1.27, \"aqi\": 1}, \"O3\": {\"concentration\": 52.21, \"aqi\": 44}, \"SO2\": {\"concentration\": 0.28, \"aqi\": 0}, \"PM2.5\": {\"concentration\": 6.79, \"aqi\": 22}, \"PM10\": {\"concentration\": 14.06, \"aqi\": 13}, \"overall_aqi\": 44}",
    "Avarua": "{\"CO\": {\"concentration\": 208.62, \"aqi\": 2}, \"NO2\": {\"concentration\": 0.07, \"aqi\": 0}, \"O3\": {\"concentration\": 55.08, \"aqi\": 46}, \"SO2\": {\"concentration\": 0.35, \"aqi\": 0}, \"PM2.5\": {\"concentration\": 4.18, \"aqi\": 13}, \"PM10\": {\"concentration\": 9.72, \"aqi\": 9}, \"overall_aqi\": 46}",
    "San Jos\u00e9": "{\"CO\": {\"concentration\": 947.95, \"aqi\": 10}, \"NO2\": {\"concentration\": 12.51, \"aqi\": 15}, \"O3\": {\"concentration\": 2.71, \"aqi\": 2}, \"SO2\": {\"concentration\": 6.8, \"aqi\": 10}, \"PM2.5\": {\"concentration\": 9.14, \"aqi\": 29}, \"PM10\": {\"concentration\": 12.65, \"aqi\": 11}, \"overall_aqi\": 29}",
    "Zagreb": "{\"CO\": {\"concentration\": 213.62, \"aqi\": 2}, \"NO2\": {\"concentration\": 1.15, \"aqi\": 1}, \"O3\": {\"concentration\": 85.83, \"aqi\": 127}, \"SO2\": {\"concentration\": 0.05, \"aqi\": 0}, \"PM2.5\": {\"concentration\": 1.34, \"aqi\": 4}, \"PM10\": {\"concentration\": 1.74, \"aqi\": 1}, \"overall_aqi\": 127}",
    "La Habana": "{\"CO\": {\"concentration\": 507.36, \"aqi\": 5}, \"NO2\": {\"concentration\": 29.47, \"aqi\": 36}, \"O3\": {\"concentration\": 49.35, \"aqi\": 41}, \"SO2\": {\"concentration\": 112.53, \"aqi\": 85}, \"PM2.5\": {\"concentration\": 26.37, \"aqi\": 71}, \"PM10\": {\"concentration\": 32.09, \"aqi\": 29}, \"overall_aqi\": 85}",
    "Nicosia": "{\"CO\": {\"concentration\": 213.62, \"aqi\": 2}, \"NO2\": {\"concentration\": 0.18, \"aqi\": 0}, \"O3\": {\"concentration\": 101.57, \"aqi\": 166}, \"SO2\": {\"concentration\": 0.33, \"aqi\": 0}, \"PM2.5\": {\"concentration\": 13.74, \"aqi\": 44}, \"PM10\": {\"concentration\": 18.65, \"aqi\": 17}, \"overall_aqi\": 166}",
    "Praha": "{\"CO\": {\"concentration\": 240.33, \"aqi\": 2}, \"NO2\": {\"concentration\": 5.66, \"aqi\": 7}, \"O3\": {\"concentration\": 100.14, \"aqi\": 162}, \"SO2\": {\"concentration\": 3.31, \"aqi\": 4}, \"PM2.5\": {\"concentration\": 6.67, \"aqi\": 21}, \"PM10\": {\"concentration\": 7.69, \"aqi\": 7}, \"overall_aqi\": 162}",
    "Copenhagen": "{\"CO\": {\"concentration\": 247, \"aqi\": 2}, \"NO2\": {\"concentration\": 7.37, \"aqi\": 9}, \"O3\": {\"concentration\": 108.72, \"aqi\": 184}, \"SO2\": {\"concentration\": 3.52, \"aqi\": 5}, \"PM2.5\": {\"concentration\": 10.27, \"aqi\": 33}, \"PM10\": {\"concentration\": 11.21, \"aqi\": 10}, \"overall_aqi\": 184}",
    "Djibouti": "{\"CO\": {\"concentration\": 247, \"aqi\": 2}, \"NO2\": {\"concentration\": 1.18, \"aqi\": 1}, \"O3\": {\"concentration\": 63.66, \"aqi\": 64}, \"SO2\": {\"concentration\": 0.95, \"aqi\": 1}, \"PM2.5\": {\"concentration\": 41.46, \"aqi\": 102}, \"PM10\": {\"concentration\": 100.82, \"aqi\": 73}, \"overall_aqi\": 102}",
    "Roseau": "{\"CO\": {\"concentration\": 230.31, \"aqi\": 2}, \"NO2\": {\"concentration\": 1.54, \"aqi\": 1}, \"O3\": {\"concentration\": 35.76, \"aqi\": 30}, \"SO2\": {\"concentration\": 0.38, \"aqi\": 0}, \"PM2.5\": {\"concentration\": 2.52, \"aqi\": 8}, \"PM10\": {\"concentration\": 3.09, \"aqi\": 2}, \"overall_aqi\": 30}",
    "Dili": "{\"CO\": {\"concentration\": 6034.85, \"aqi\": 66}, \"NO2\": {\"concentration\": 115.16, \"aqi\": 119}, \"O3\": {\"concentration\": 0.56, \"aqi\": 0}, \"SO2\": {\"concentration\": 54.36, \"aqi\": 59}, \"PM2.5\": {\"concentration\": 638.99, \"aqi\": 500}, \"PM10\": {\"concentration\": 832.84, \"aqi\": 500}, \"overall_aqi\": 500}",
    "Quito": "{\"CO\": {\"concentration\": 2723.69, \"aqi\": 30}, \"NO2\": {\"concentration\": 91.85, \"aqi\": 106}, \"O3\": {\"concentration\": 80.11, \"aqi\": 112}, \"SO2\": {\"concentration\": 31.95, \"aqi\": 46}, \"PM2.5\": {\"concentration\": 49.26, \"aqi\": 117}, \"PM10\": {\"concentration\": 53.72, \"aqi\": 49}, \"overall_aqi\": 117}",
    "Cairo": "{\"CO\": {\"concentration\": 220.3, \"aqi\": 2}, \"NO2\": {\"concentration\": 5.27, \"aqi\": 6}, \"O3\": {\"concentration\": 150.2, \"aqi\": 213}, \"SO2\": {\"concentration\": 6.44, \"aqi\": 9}, \"PM2.5\": {\"concentration\": 14.73, \"aqi\": 47}, \"PM10\": {\"concentration\": 26.48, \"aqi\": 24}, \"overall_aqi\": 213}",
    "San Salvador": "{\"CO\": {\"concentration\": 1214.98, \"aqi\": 13}, \"NO2\": {\"concentration\": 20.22, \"aqi\": 25}, \"O3\": {\"concentration\": 69.38, \"aqi\": 82}, \"SO2\": {\"concentration\": 43.39, \"aqi\": 54}, \"PM2.5\": {\"concentration\": 43.34, \"aqi\": 105}, \"PM10\": {\"concentration\": 60.57, \"aqi\": 53}, \"overall_aqi\": 105}",
    "London": "{\"CO\": {\"concentration\": 233.65, \"aqi\": 2}, \"NO2\": {\"concentration\": 10.71, \"aqi\": 13}, \"O3\": {\"concentration\": 67.23, \"aqi\": 75}, \"SO2\": {\"concentration\": 7.87, \"aqi\": 11}, \"PM2.5\": {\"concentration\": 2.65, \"aqi\": 8}, \"PM10\": {\"concentration\": 3.89, \"aqi\": 3}, \"overall_aqi\": 75}",
    "Malabo": "{\"CO\": {\"concentration\": 400.54, \"aqi\": 4}, \"NO2\": {\"concentration\": 0.02, \"aqi\": 0}, \"O3\": {\"concentration\": 34.33, \"aqi\": 29}, \"SO2\": {\"concentration\": 0.04, \"aqi\": 0}, \"PM2.5\": {\"concentration\": 1.45, \"aqi\": 4}, \"PM10\": {\"concentration\": 1.87, \"aqi\": 1}, \"overall_aqi\": 29}",
    "Asmara": "{\"CO\": {\"concentration\": 180.24, \"aqi\": 2}, \"NO2\": {\"concentration\": 0.35, \"aqi\": 0}, \"O3\": {\"concentration\": 86.55, \"aqi\": 128}, \"SO2\": {\"concentration\": 1.37, \"aqi\": 2}, \"PM2.5\": {\"concentration\": 34.53, \"aqi\": 88}, \"PM10\": {\"concentration\": 102.67, \"aqi\": 74}, \"overall_aqi\": 128}",
    "Tallinn": "{\"CO\": {\"concentration\": 236.99, \"aqi\": 2}, \"NO2\": {\"concentration\": 3.17, \"aqi\": 3}, \"O3\": {\"concentration\": 77.25, \"aqi\": 105}, \"SO2\": {\"concentration\": 1.55, \"aqi\": 2}, \"PM2.5\": {\"concentration\": 6.11, \"aqi\": 19}, \"PM10\": {\"concentration\": 7.53, \"aqi\": 6}, \"overall_aqi\": 105}",
    "Addis Abeba": "{\"CO\": {\"concentration\": 2536.77, \"aqi\": 28}, \"NO2\": {\"concentration\": 3.68, \"aqi\": 4}, \"O3\": {\"concentration\": 42.56, \"aqi\": 36}, \"SO2\": {\"concentration\": 2.65, \"aqi\": 3}, \"PM2.5\": {\"concentration\": 56.09, \"aqi\": 131}, \"PM10\": {\"concentration\": 147.75, \"aqi\": 96}, \"overall_aqi\": 131}",
    "Stanley": "{\"CO\": {\"concentration\": 220.3, \"aqi\": 2}, \"NO2\": {\"concentration\": 0.01, \"aqi\": 0}, \"O3\": {\"concentration\": 50.07, \"aqi\": 42}, \"SO2\": {\"concentration\": 0.13, \"aqi\": 0}, \"PM2.5\": {\"concentration\": 0.5, \"aqi\": 1}, \"PM10\": {\"concentration\": 0.75, \"aqi\": 0}, \"overall_aqi\": 42}",
    "T\u00f3rshavn": "{\"CO\": {\"concentration\": 226.97, \"aqi\": 2}, \"NO2\": {\"concentration\": 0.08, \"aqi\": 0}, \"O3\": {\"concentration\": 59.37, \"aqi\": 51}, \"SO2\": {\"concentration\": 0.48, \"aqi\": 0}, \"PM2.5\": {\"concentration\": 3.81, \"aqi\": 12}, \"PM10\": {\"concentration\": 9.23, \"aqi\": 8}, \"overall_aqi\": 51}",
    "Suva": "{\"CO\": {\"concentration\": 205.28, \"aqi\": 2}, \"NO2\": {\"concentration\": 2.59, \"aqi\": 3}, \"O3\": {\"concentration\": 24.32, \"aqi\": 20}, \"SO2\": {\"concentration\": 2.03, \"aqi\": 2}, \"PM2.5\": {\"concentration\": 4.79, \"aqi\": 15}, \"PM10\": {\"concentration\": 5.78, \"aqi\": 5}, \"overall_aqi\": 20}",
    "Helsinki [Helsingfors]": "{\"CO\": {\"concentration\": 230.31, \"aqi\": 2}, \"NO2\": {\"concentration\": 4.33, \"aqi\": 5}, \"O3\": {\"concentration\": 79.39, \"aqi\": 110}, \"SO2\": {\"concentration\": 1.46, \"aqi\": 2}, \"PM2.5\": {\"concentration\": 6.19, \"aqi\": 20}, \"PM10\": {\"concentration\": 8.64, \"aqi\": 8}, \"overall_aqi\": 110}",
    "Paris": "{\"CO\": {\"concentration\": 263.69, \"aqi\": 2}, \"NO2\": {\"concentration\": 10.54, \"aqi\": 13}, \"O3\": {\"concentration\": 47.92, \"aqi\": 40}, \"SO2\": {\"concentration\": 1.86, \"aqi\": 2}, \"PM2.5\": {\"concentration\": 2.55, \"aqi\": 8}, \"PM10\": {\"concentration\": 3.5, \"aqi\": 3}, \"overall_aqi\": 40}",
    "Cayenne": "{\"CO\": {\"concentration\": 307.08, \"aqi\": 3}, \"NO2\": {\"concentration\": 0.27, \"aqi\": 0}, \"O3\": {\"concentration\": 50.78, \"aqi\": 43}, \"SO2\": {\"concentration\": 0.32, \"aqi\": 0}, \"PM2.5\": {\"concentration\": 3.2, \"aqi\": 10}, \"PM10\": {\"concentration\": 8.37, \"aqi\": 7}, \"overall_aqi\": 43}",
    "Papeete": "{\"CO\": {\"concentration\": 223.64, \"aqi\": 2}, \"NO2\": {\"concentration\": 2.61, \"aqi\": 3}, \"O3\": {\"concentration\": 57.22, \"aqi\": 48}, \"SO2\": {\"concentration\": 2.12, \"aqi\": 3}, \"PM2.5\": {\"concentration\": 2.06, \"aqi\": 6}, \"PM10\": {\"concentration\": 4.63, \"aqi\": 4}, \"overall_aqi\": 48}",
    "Libreville": "{\"CO\": {\"concentration\": 534.06, \"aqi\": 6}, \"NO2\": {\"concentration\": 3.09, \"aqi\": 3}, \"O3\": {\"concentration\": 36.12, \"aqi\": 30}, \"SO2\": {\"concentration\": 2.95, \"aqi\": 4}, \"PM2.5\": {\"concentration\": 6.64, \"aqi\": 21}, \"PM10\": {\"concentration\": 11.93, \"aqi\": 11}, \"overall_aqi\": 30}",
    "Banjul": "{\"CO\": {\"concentration\": 320.44, \"aqi\": 3}, \"NO2\": {\"concentration\": 0.58, \"aqi\": 0}, \"O3\": {\"concentration\": 40.41, \"aqi\": 34}, \"SO2\": {\"concentration\": 0.8, \"aqi\": 1}, \"PM2.5\": {\"concentration\": 2.92, \"aqi\": 9}, \"PM10\": {\"concentration\": 5.16, \"aqi\": 4}, \"overall_aqi\": 34}",
    "Tbilisi": "{\"CO\": {\"concentration\": 390.53, \"aqi\": 4}, \"NO2\": {\"concentration\": 13.88, \"aqi\": 17}, \"O3\": {\"concentration\": 50.78, \"aqi\": 43}, \"SO2\": {\"concentration\": 1.27, \"aqi\": 1}, \"PM2.5\": {\"concentration\": 11.36, \"aqi\": 36}, \"PM10\": {\"concentration\": 13.67, \"aqi\": 12}, \"overall_aqi\": 43}",
    "Berlin": "{\"CO\": {\"concentration\": 260.35, \"aqi\": 2}, \"NO2\": {\"concentration\": 10.71, \"aqi\": 13}, \"O3\": {\"concentration\": 108.72, \"aqi\": 184}, \"SO2\": {\"concentration\": 6.38, \"aqi\": 9}, \"PM2.5\": {\"concentration\": 11.33, \"aqi\": 36}, \"PM10\": {\"concentration\": 12.64, \"aqi\": 11}, \"overall_aqi\": 184}",
    "Accra": "{\"CO\": {\"concentration\": 413.9, \"aqi\": 4}, \"NO2\": {\"concentration\": 1.3, \"aqi\": 1}, \"O3\": {\"concentration\": 31.83, \"aqi\": 26}, \"SO2\": {\"concentration\": 0.83, \"aqi\": 1}, \"PM2.5\": {\"concentration\": 3.89, \"aqi\": 12}, \"PM10\": {\"concentration\": 9.8, \"aqi\": 9}, \"overall_aqi\": 26}",
    "Gibraltar": "{\"CO\": {\"concentration\": 213.62, \"aqi\": 2}, \"NO2\": {\"concentration\": 1.44, \"aqi\": 1}, \"O3\": {\"concentration\": 89.41, \"aqi\": 136}, \"SO2\": {\"concentration\": 1.15, \"aqi\": 1}, \"PM2.5\": {\"concentration\": 1.26, \"aqi\": 4}, \"PM10\": {\"concentration\": 2.95, \"aqi\": 2}, \"overall_aqi\": 136}",
    "Athenai": "{\"CO\": {\"concentration\": 236.99, \"aqi\": 2}, \"NO2\": {\"concentration\": 7.37, \"aqi\": 9}, \"O3\": {\"concentration\": 153.07, \"aqi\": 214}, \"SO2\": {\"concentration\": 11.68, \"aqi\": 17}, \"PM2.5\": {\"concentration\": 20.73, \"aqi\": 60}, \"PM10\": {\"concentration\": 24.95, \"aqi\": 23}, \"overall_aqi\": 214}",
    "Nuuk": "{\"CO\": {\"concentration\": 233.65, \"aqi\": 2}, \"NO2\": {\"concentration\": 0.3, \"aqi\": 0}, \"O3\": {\"concentration\": 67.95, \"aqi\": 77}, \"SO2\": {\"concentration\": 0.3, \"aqi\": 0}, \"PM2.5\": {\"concentration\": 1.09, \"aqi\": 3}, \"PM10\": {\"concentration\": 4.68, \"aqi\": 4}, \"overall_aqi\": 77}",
    "Saint George's": "{\"CO\": {\"concentration\": 287.06, \"aqi\": 3}, \"NO2\": {\"concentration\": 1.56, \"aqi\": 1}, \"O3\": {\"concentration\": 22.17, \"aqi\": 18}, \"SO2\": {\"concentration\": 1.15, \"aqi\": 1}, \"PM2.5\": {\"concentration\": 0.97, \"aqi\": 3}, \"PM10\": {\"concentration\": 1.64, \"aqi\": 1}, \"overall_aqi\": 18}",
    "Basse-Terre": "{\"CO\": {\"concentration\": 233.65, \"aqi\": 2}, \"NO2\": {\"concentration\": 9.34, \"aqi\": 11}, \"O3\": {\"concentration\": 44.35, \"aqi\": 37}, \"SO2\": {\"concentration\": 11.09, \"aqi\": 16}, \"PM2.5\": {\"concentration\": 3.7, \"aqi\": 12}, \"PM10\": {\"concentration\": 4.68, \"aqi\": 4}, \"overall_aqi\": 37}",
    "Aga": "{\"CO\": {\"concentration\": 236.99, \"aqi\": 2}, \"NO2\": {\"concentration\": 4.03, \"aqi\": 5}, \"O3\": {\"concentration\": 52.93, \"aqi\": 44}, \"SO2\": {\"concentration\": 1.34, \"aqi\": 1}, \"PM2.5\": {\"concentration\": 5.06, \"aqi\": 16}, \"PM10\": {\"concentration\": 6.34, \"aqi\": 5}, \"overall_aqi\": 44}",
    "Ciudad de Guatemala": "{\"CO\": {\"concentration\": 1468.66, \"aqi\": 16}, \"NO2\": {\"concentration\": 12, \"aqi\": 15}, \"O3\": {\"concentration\": 81.54, \"aqi\": 116}, \"SO2\": {\"concentration\": 19.31, \"aqi\": 28}, \"PM2.5\": {\"concentration\": 127.69, \"aqi\": 186}, \"PM10\": {\"concentration\": 200.33, \"aqi\": 123}, \"overall_aqi\": 186}",
    "Conakry": "{\"CO\": {\"concentration\": 280.38, \"aqi\": 3}, \"NO2\": {\"concentration\": 0.1, \"aqi\": 0}, \"O3\": {\"concentration\": 39.34, \"aqi\": 33}, \"SO2\": {\"concentration\": 0.04, \"aqi\": 0}, \"PM2.5\": {\"concentration\": 1.3, \"aqi\": 4}, \"PM10\": {\"concentration\": 10.79, \"aqi\": 9}, \"overall_aqi\": 33}",
    "Bissau": "{\"CO\": {\"concentration\": 287.06, \"aqi\": 3}, \"NO2\": {\"concentration\": 0.53, \"aqi\": 0}, \"O3\": {\"concentration\": 29.68, \"aqi\": 25}, \"SO2\": {\"concentration\": 1.04, \"aqi\": 1}, \"PM2.5\": {\"concentration\": 1.95, \"aqi\": 6}, \"PM10\": {\"concentration\": 3.32, \"aqi\": 3}, \"overall_aqi\": 25}",
    "Georgetown": "{\"CO\": {\"concentration\": 317.1, \"aqi\": 3}, \"NO2\": {\"concentration\": 5.83, \"aqi\": 7}, \"O3\": {\"concentration\": 38.62, \"aqi\": 32}, \"SO2\": {\"concentration\": 6.26, \"aqi\": 9}, \"PM2.5\": {\"concentration\": 1.3, \"aqi\": 4}, \"PM10\": {\"concentration\": 2.25, \"aqi\": 2}, \"overall_aqi\": 32}",
    "Port-au-Prince": "{\"CO\": {\"concentration\": 734.33, \"aqi\": 8}, \"NO2\": {\"concentration\": 6.77, \"aqi\": 8}, \"O3\": {\"concentration\": 170.23, \"aqi\": 221}, \"SO2\": {\"concentration\": 11.92, \"aqi\": 17}, \"PM2.5\": {\"concentration\": 24.63, \"aqi\": 68}, \"PM10\": {\"concentration\": 36.14, \"aqi\": 33}, \"overall_aqi\": 221}",
    "Citt": "{\"CO\": {\"concentration\": 293.73, \"aqi\": 3}, \"NO2\": {\"concentration\": 5.57, \"aqi\": 6}, \"O3\": {\"concentration\": 38.98, \"aqi\": 33}, \"SO2\": {\"concentration\": 0.24, \"aqi\": 0}, \"PM2.5\": {\"concentration\": 4.87, \"aqi\": 15}, \"PM10\": {\"concentration\": 5, \"aqi\": 4}, \"overall_aqi\": 33}",
    "Tegucigalpa": "{\"CO\": {\"concentration\": 300.41, \"aqi\": 3}, \"NO2\": {\"concentration\": 3.43, \"aqi\": 4}, \"O3\": {\"concentration\": 22.89, \"aqi\": 19}, \"SO2\": {\"concentration\": 1.03, \"aqi\": 1}, \"PM2.5\": {\"concentration\": 1.03, \"aqi\": 3}, \"PM10\": {\"concentration\": 4.99, \"aqi\": 4}, \"overall_aqi\": 19}",
    "Victoria": "{\"CO\": {\"concentration\": 230.31, \"aqi\": 2}, \"NO2\": {\"concentration\": 9, \"aqi\": 11}, \"O3\": {\"concentration\": 15.38, \"aqi\": 13}, \"SO2\": {\"concentration\": 1.42, \"aqi\": 2}, \"PM2.5\": {\"concentration\": 1.41, \"aqi\": 4}, \"PM10\": {\"concentration\": 2.12, \"aqi\": 1}, \"overall_aqi\": 13}",
    "Budapest": "{\"CO\": {\"concentration\": 226.97, \"aqi\": 2}, \"NO2\": {\"concentration\": 5.83, \"aqi\": 7}, \"O3\": {\"concentration\": 77.96, \"aqi\": 107}, \"SO2\": {\"concentration\": 5.54, \"aqi\": 8}, \"PM2.5\": {\"concentration\": 15.13, \"aqi\": 49}, \"PM10\": {\"concentration\": 15.97, \"aqi\": 14}, \"overall_aqi\": 107}",
    "Reykjav\u00edk": "{\"CO\": {\"concentration\": 230.31, \"aqi\": 2}, \"NO2\": {\"concentration\": 0.15, \"aqi\": 0}, \"O3\": {\"concentration\": 67.23, \"aqi\": 75}, \"SO2\": {\"concentration\": 0.79, \"aqi\": 1}, \"PM2.5\": {\"concentration\": 0.5, \"aqi\": 1}, \"PM10\": {\"concentration\": 1.04, \"aqi\": 0}, \"overall_aqi\": 75}",
    "New Delhi": "{\"CO\": {\"concentration\": 6034.85, \"aqi\": 66}, \"NO2\": {\"concentration\": 115.16, \"aqi\": 119}, \"O3\": {\"concentration\": 0.56, \"aqi\": 0}, \"SO2\": {\"concentration\": 54.36, \"aqi\": 59}, \"PM2.5\": {\"concentration\": 638.99, \"aqi\": 500}, \"PM10\": {\"concentration\": 832.84, \"aqi\": 500}, \"overall_aqi\": 500}",
    "Jakarta": "{\"CO\": {\"concentration\": 417.23, \"aqi\": 4}, \"NO2\": {\"concentration\": 16.28, \"aqi\": 20}, \"O3\": {\"concentration\": 98.71, \"aqi\": 159}, \"SO2\": {\"concentration\": 20.5, \"aqi\": 30}, \"PM2.5\": {\"concentration\": 61.43, \"aqi\": 142}, \"PM10\": {\"concentration\": 71.59, \"aqi\": 58}, \"overall_aqi\": 159}",
    "Tehran": "{\"CO\": {\"concentration\": 1455.31, \"aqi\": 16}, \"NO2\": {\"concentration\": 134.35, \"aqi\": 130}, \"O3\": {\"concentration\": 0.12, \"aqi\": 0}, \"SO2\": {\"concentration\": 82.97, \"aqi\": 72}, \"PM2.5\": {\"concentration\": 22.32, \"aqi\": 63}, \"PM10\": {\"concentration\": 66.05, \"aqi\": 56}, \"overall_aqi\": 130}",
    "Baghdad": "{\"CO\": {\"concentration\": 1081.47, \"aqi\": 12}, \"NO2\": {\"concentration\": 132.98, \"aqi\": 130}, \"O3\": {\"concentration\": 31.11, \"aqi\": 26}, \"SO2\": {\"concentration\": 53.41, \"aqi\": 58}, \"PM2.5\": {\"concentration\": 31.18, \"aqi\": 81}, \"PM10\": {\"concentration\": 46.56, \"aqi\": 43}, \"overall_aqi\": 130}",
    "Dublin": "{\"CO\": {\"concentration\": 226.97, \"aqi\": 2}, \"NO2\": {\"concentration\": 2.1, \"aqi\": 2}, \"O3\": {\"concentration\": 55.08, \"aqi\": 46}, \"SO2\": {\"concentration\": 1.01, \"aqi\": 1}, \"PM2.5\": {\"concentration\": 0.5, \"aqi\": 1}, \"PM10\": {\"concentration\": 0.65, \"aqi\": 0}, \"overall_aqi\": 46}",
    "Jerusalem": "{\"CO\": {\"concentration\": 205.28, \"aqi\": 2}, \"NO2\": {\"concentration\": 5.74, \"aqi\": 7}, \"O3\": {\"concentration\": 120.16, \"aqi\": 201}, \"SO2\": {\"concentration\": 2.03, \"aqi\": 2}, \"PM2.5\": {\"concentration\": 14.5, \"aqi\": 47}, \"PM10\": {\"concentration\": 23.2, \"aqi\": 21}, \"overall_aqi\": 201}",
    "Roma": "{\"CO\": {\"concentration\": 243.66, \"aqi\": 2}, \"NO2\": {\"concentration\": 4.16, \"aqi\": 5}, \"O3\": {\"concentration\": 87.98, \"aqi\": 132}, \"SO2\": {\"concentration\": 0.57, \"aqi\": 0}, \"PM2.5\": {\"concentration\": 19.64, \"aqi\": 58}, \"PM10\": {\"concentration\": 49.34, \"aqi\": 45}, \"overall_aqi\": 132}",
    "Yamoussoukro": "{\"CO\": {\"concentration\": 353.81, \"aqi\": 4}, \"NO2\": {\"concentration\": 0.28, \"aqi\": 0}, \"O3\": {\"concentration\": 19.49, \"aqi\": 16}, \"SO2\": {\"concentration\": 0.1, \"aqi\": 0}, \"PM2.5\": {\"concentration\": 1.22, \"aqi\": 3}, \"PM10\": {\"concentration\": 2.1, \"aqi\": 1}, \"overall_aqi\": 16}",
    "Kingston": "{\"CO\": {\"concentration\": 1174.93, \"aqi\": 13}, \"NO2\": {\"concentration\": 19.19, \"aqi\": 23}, \"O3\": {\"concentration\": 60.08, \"aqi\": 53}, \"SO2\": {\"concentration\": 12.76, \"aqi\": 18}, \"PM2.5\": {\"concentration\": 23.61, \"aqi\": 66}, \"PM10\": {\"concentration\": 32.23, \"aqi\": 29}, \"overall_aqi\": 66}",
    "Tokyo": "{\"CO\": {\"concentration\": 175.24, \"aqi\": 1}, \"NO2\": {\"concentration\": 20.91, \"aqi\": 26}, \"O3\": {\"concentration\": 22.89, \"aqi\": 19}, \"SO2\": {\"concentration\": 10.49, \"aqi\": 15}, \"PM2.5\": {\"concentration\": 2.77, \"aqi\": 8}, \"PM10\": {\"concentration\": 3.83, \"aqi\": 3}, \"overall_aqi\": 26}",
    "Amman": "{\"CO\": {\"concentration\": 206.95, \"aqi\": 2}, \"NO2\": {\"concentration\": 9.68, \"aqi\": 12}, \"O3\": {\"concentration\": 155.93, \"aqi\": 215}, \"SO2\": {\"concentration\": 4.47, \"aqi\": 6}, \"PM2.5\": {\"concentration\": 16.78, \"aqi\": 52}, \"PM10\": {\"concentration\": 26.62, \"aqi\": 24}, \"overall_aqi\": 215}",
    "Astana": "{\"CO\": {\"concentration\": 357.15, \"aqi\": 4}, \"NO2\": {\"concentration\": 20.91, \"aqi\": 26}, \"O3\": {\"concentration\": 0.09, \"aqi\": 0}, \"SO2\": {\"concentration\": 30.04, \"aqi\": 44}, \"PM2.5\": {\"concentration\": 14.39, \"aqi\": 46}, \"PM10\": {\"concentration\": 15.58, \"aqi\": 14}, \"overall_aqi\": 46}",
    "Nairobi": "{\"CO\": {\"concentration\": 700.95, \"aqi\": 7}, \"NO2\": {\"concentration\": 9.77, \"aqi\": 12}, \"O3\": {\"concentration\": 58.65, \"aqi\": 49}, \"SO2\": {\"concentration\": 9.18, \"aqi\": 13}, \"PM2.5\": {\"concentration\": 13.83, \"aqi\": 44}, \"PM10\": {\"concentration\": 28.74, \"aqi\": 26}, \"overall_aqi\": 49}",
    "Bairiki": "{\"CO\": {\"concentration\": 168.56, \"aqi\": 1}, \"NO2\": {\"concentration\": 0.01, \"aqi\": 0}, \"O3\": {\"concentration\": 13.59, \"aqi\": 11}, \"SO2\": {\"concentration\": 0.01, \"aqi\": 0}, \"PM2.5\": {\"concentration\": 0.5, \"aqi\": 1}, \"PM10\": {\"concentration\": 0.89, \"aqi\": 0}, \"overall_aqi\": 11}",
    "Kuwait": "{\"CO\": {\"concentration\": 236.99, \"aqi\": 2}, \"NO2\": {\"concentration\": 11.48, \"aqi\": 14}, \"O3\": {\"concentration\": 153.07, \"aqi\": 214}, \"SO2\": {\"concentration\": 4.89, \"aqi\": 7}, \"PM2.5\": {\"concentration\": 27.14, \"aqi\": 73}, \"PM10\": {\"concentration\": 84.45, \"aqi\": 65}, \"overall_aqi\": 214}",
    "Bishkek": "{\"CO\": {\"concentration\": 220.3, \"aqi\": 2}, \"NO2\": {\"concentration\": 5.27, \"aqi\": 6}, \"O3\": {\"concentration\": 53.64, \"aqi\": 45}, \"SO2\": {\"concentration\": 1.06, \"aqi\": 1}, \"PM2.5\": {\"concentration\": 2.01, \"aqi\": 6}, \"PM10\": {\"concentration\": 3.6, \"aqi\": 3}, \"overall_aqi\": 45}",
    "Vientiane": "{\"CO\": {\"concentration\": 2883.91, \"aqi\": 32}, \"NO2\": {\"concentration\": 27.08, \"aqi\": 33}, \"O3\": {\"concentration\": 0.07, \"aqi\": 0}, \"SO2\": {\"concentration\": 4.95, \"aqi\": 7}, \"PM2.5\": {\"concentration\": 42.22, \"aqi\": 103}, \"PM10\": {\"concentration\": 52.23, \"aqi\": 48}, \"overall_aqi\": 103}",
    "Riga": "{\"CO\": {\"concentration\": 253.68, \"aqi\": 2}, \"NO2\": {\"concentration\": 5.18, \"aqi\": 6}, \"O3\": {\"concentration\": 87.98, \"aqi\": 132}, \"SO2\": {\"concentration\": 2.77, \"aqi\": 4}, \"PM2.5\": {\"concentration\": 11.13, \"aqi\": 36}, \"PM10\": {\"concentration\": 13.17, \"aqi\": 12}, \"overall_aqi\": 132}",
    "Beirut": "{\"CO\": {\"concentration\": 213.62, \"aqi\": 2}, \"NO2\": {\"concentration\": 0.4, \"aqi\": 0}, \"O3\": {\"concentration\": 101.57, \"aqi\": 166}, \"SO2\": {\"concentration\": 1.24, \"aqi\": 1}, \"PM2.5\": {\"concentration\": 14.89, \"aqi\": 48}, \"PM10\": {\"concentration\": 20.45, \"aqi\": 18}, \"overall_aqi\": 166}",
    "Maseru": "{\"CO\": {\"concentration\": 273.71, \"aqi\": 3}, \"NO2\": {\"concentration\": 0.41, \"aqi\": 0}, \"O3\": {\"concentration\": 69.38, \"aqi\": 82}, \"SO2\": {\"concentration\": 0.62, \"aqi\": 0}, \"PM2.5\": {\"concentration\": 2.07, \"aqi\": 6}, \"PM10\": {\"concentration\": 4.22, \"aqi\": 3}, \"overall_aqi\": 82}",
    "Monrovia": "{\"CO\": {\"concentration\": 473.98, \"aqi\": 5}, \"NO2\": {\"concentration\": 1.26, \"aqi\": 1}, \"O3\": {\"concentration\": 41.84, \"aqi\": 35}, \"SO2\": {\"concentration\": 1.25, \"aqi\": 1}, \"PM2.5\": {\"concentration\": 4.21, \"aqi\": 13}, \"PM10\": {\"concentration\": 7.43, \"aqi\": 6}, \"overall_aqi\": 35}",
    "Tripoli": "{\"CO\": {\"concentration\": 397.21, \"aqi\": 4}, \"NO2\": {\"concentration\": 8.65, \"aqi\": 10}, \"O3\": {\"concentration\": 181.68, \"aqi\": 225}, \"SO2\": {\"concentration\": 0.9, \"aqi\": 1}, \"PM2.5\": {\"concentration\": 27.94, \"aqi\": 75}, \"PM10\": {\"concentration\": 60.62, \"aqi\": 53}, \"overall_aqi\": 225}",
    "Vaduz": "{\"CO\": {\"concentration\": 200.27, \"aqi\": 2}, \"NO2\": {\"concentration\": 1.69, \"aqi\": 2}, \"O3\": {\"concentration\": 67.23, \"aqi\": 75}, \"SO2\": {\"concentration\": 0.36, \"aqi\": 0}, \"PM2.5\": {\"concentration\": 1.66, \"aqi\": 5}, \"PM10\": {\"concentration\": 1.86, \"aqi\": 1}, \"overall_aqi\": 75}",
    "Vilnius": "{\"CO\": {\"concentration\": 240.33, \"aqi\": 2}, \"NO2\": {\"concentration\": 4.97, \"aqi\": 6}, \"O3\": {\"concentration\": 98.71, \"aqi\": 159}, \"SO2\": {\"concentration\": 3.7, \"aqi\": 5}, \"PM2.5\": {\"concentration\": 13.95, \"aqi\": 45}, \"PM10\": {\"concentration\": 15.42, \"aqi\": 14}, \"overall_aqi\": 159}",
    "Macao": "{\"CO\": {\"concentration\": 587.46, \"aqi\": 6}, \"NO2\": {\"concentration\": 56.21, \"aqi\": 70}, \"O3\": {\"concentration\": 0, \"aqi\": 0}, \"SO2\": {\"concentration\": 24.56, \"aqi\": 36}, \"PM2.5\": {\"concentration\": 79.73, \"aqi\": 158}, \"PM10\": {\"concentration\": 112.54, \"aqi\": 79}, \"overall_aqi\": 158}",
    "Skopje": "{\"CO\": {\"concentration\": 203.61, \"aqi\": 2}, \"NO2\": {\"concentration\": 1.46, \"aqi\": 1}, \"O3\": {\"concentration\": 91.55, \"aqi\": 141}, \"SO2\": {\"concentration\": 2.98, \"aqi\": 4}, \"PM2.5\": {\"concentration\": 6.71, \"aqi\": 21}, \"PM10\": {\"concentration\": 14.12, \"aqi\": 13}, \"overall_aqi\": 141}",
    "Antananarivo": "{\"CO\": {\"concentration\": 440.6, \"aqi\": 5}, \"NO2\": {\"concentration\": 2.19, \"aqi\": 2}, \"O3\": {\"concentration\": 74.39, \"aqi\": 98}, \"SO2\": {\"concentration\": 2.09, \"aqi\": 3}, \"PM2.5\": {\"concentration\": 8.61, \"aqi\": 27}, \"PM10\": {\"concentration\": 13.9, \"aqi\": 12}, \"overall_aqi\": 98}",
    "Lilongwe": "{\"CO\": {\"concentration\": 300.41, \"aqi\": 3}, \"NO2\": {\"concentration\": 0.53, \"aqi\": 0}, \"O3\": {\"concentration\": 69.38, \"aqi\": 82}, \"SO2\": {\"concentration\": 0.33, \"aqi\": 0}, \"PM2.5\": {\"concentration\": 7.92, \"aqi\": 25}, \"PM10\": {\"concentration\": 10.02, \"aqi\": 9}, \"overall_aqi\": 82}",
    "Kuala Lumpur": "{\"CO\": {\"concentration\": 2643.59, \"aqi\": 30}, \"NO2\": {\"concentration\": 42.5, \"aqi\": 53}, \"O3\": {\"concentration\": 0, \"aqi\": 0}, \"SO2\": {\"concentration\": 25.27, \"aqi\": 37}, \"PM2.5\": {\"concentration\": 44.57, \"aqi\": 108}, \"PM10\": {\"concentration\": 56.21, \"aqi\": 51}, \"overall_aqi\": 108}",
    "Male": "{\"CO\": {\"concentration\": 313.76, \"aqi\": 3}, \"NO2\": {\"concentration\": 0.1, \"aqi\": 0}, \"O3\": {\"concentration\": 44.35, \"aqi\": 37}, \"SO2\": {\"concentration\": 0.05, \"aqi\": 0}, \"PM2.5\": {\"concentration\": 1.61, \"aqi\": 5}, \"PM10\": {\"concentration\": 2.1, \"aqi\": 1}, \"overall_aqi\": 37}",
    "Bamako": "{\"CO\": {\"concentration\": 277.04, \"aqi\": 3}, \"NO2\": {\"concentration\": 0.16, \"aqi\": 0}, \"O3\": {\"concentration\": 8.58, \"aqi\": 7}, \"SO2\": {\"concentration\": 0.09, \"aqi\": 0}, \"PM2.5\": {\"concentration\": 1.33, \"aqi\": 4}, \"PM10\": {\"concentration\": 4.67, \"aqi\": 4}, \"overall_aqi\": 7}",
    "Valletta": "{\"CO\": {\"concentration\": 211.95, \"aqi\": 2}, \"NO2\": {\"concentration\": 1.93, \"aqi\": 2}, \"O3\": {\"concentration\": 75.1, \"aqi\": 100}, \"SO2\": {\"concentration\": 0.52, \"aqi\": 0}, \"PM2.5\": {\"concentration\": 23.85, \"aqi\": 66}, \"PM10\": {\"concentration\": 62.53, \"aqi\": 54}, \"overall_aqi\": 100}",
    "Dalap-Uliga-Darrit": "{\"CO\": {\"concentration\": 163.56, \"aqi\": 1}, \"NO2\": {\"concentration\": 0, \"aqi\": 0}, \"O3\": {\"concentration\": 16.99, \"aqi\": 14}, \"SO2\": {\"concentration\": 0.05, \"aqi\": 0}, \"PM2.5\": {\"concentration\": 0.64, \"aqi\": 2}, \"PM10\": {\"concentration\": 1.86, \"aqi\": 1}, \"overall_aqi\": 14}",
    "Fort-de-France": "{\"CO\": {\"concentration\": 223.64, \"aqi\": 2}, \"NO2\": {\"concentration\": 2.83, \"aqi\": 3}, \"O3\": {\"concentration\": 29.33, \"aqi\": 24}, \"SO2\": {\"concentration\": 1.94, \"aqi\": 2}, \"PM2.5\": {\"concentration\": 2.95, \"aqi\": 9}, \"PM10\": {\"concentration\": 4.04, \"aqi\": 3}, \"overall_aqi\": 24}",
    "Nouakchott": "{\"CO\": {\"concentration\": 277.04, \"aqi\": 3}, \"NO2\": {\"concentration\": 0.21, \"aqi\": 0}, \"O3\": {\"concentration\": 50.78, \"aqi\": 43}, \"SO2\": {\"concentration\": 0.47, \"aqi\": 0}, \"PM2.5\": {\"concentration\": 32.06, \"aqi\": 83}, \"PM10\": {\"concentration\": 126.33, \"aqi\": 86}, \"overall_aqi\": 86}",
    "Port-Louis": "{\"CO\": {\"concentration\": 216.96, \"aqi\": 2}, \"NO2\": {\"concentration\": 2.21, \"aqi\": 2}, \"O3\": {\"concentration\": 41.84, \"aqi\": 35}, \"SO2\": {\"concentration\": 2.68, \"aqi\": 3}, \"PM2.5\": {\"concentration\": 7.56, \"aqi\": 24}, \"PM10\": {\"concentration\": 13.48, \"aqi\": 12}, \"overall_aqi\": 35}",
    "Ciudad de M": "{\"CO\": {\"concentration\": 205.28, \"aqi\": 2}, \"NO2\": {\"concentration\": 5.74, \"aqi\": 7}, \"O3\": {\"concentration\": 120.16, \"aqi\": 201}, \"SO2\": {\"concentration\": 2.03, \"aqi\": 2}, \"PM2.5\": {\"concentration\": 14.5, \"aqi\": 47}, \"PM10\": {\"concentration\": 23.2, \"aqi\": 21}, \"overall_aqi\": 201}",
    "Palikir": "{\"CO\": {\"concentration\": 208.62, \"aqi\": 2}, \"NO2\": {\"concentration\": 0.02, \"aqi\": 0}, \"O3\": {\"concentration\": 37.55, \"aqi\": 31}, \"SO2\": {\"concentration\": 0.05, \"aqi\": 0}, \"PM2.5\": {\"concentration\": 0.6, \"aqi\": 1}, \"PM10\": {\"concentration\": 1.48, \"aqi\": 1}, \"overall_aqi\": 31}",
    "Chisinau": "{\"CO\": {\"concentration\": 233.65, \"aqi\": 2}, \"NO2\": {\"concentration\": 4.58, \"aqi\": 5}, \"O3\": {\"concentration\": 72.24, \"aqi\": 91}, \"SO2\": {\"concentration\": 2.15, \"aqi\": 3}, \"PM2.5\": {\"concentration\": 5.3, \"aqi\": 17}, \"PM10\": {\"concentration\": 5.5, \"aqi\": 5}, \"overall_aqi\": 91}",
    "Monaco-Ville": "{\"CO\": {\"concentration\": 216.96, \"aqi\": 2}, \"NO2\": {\"concentration\": 2.16, \"aqi\": 2}, \"O3\": {\"concentration\": 79.39, \"aqi\": 110}, \"SO2\": {\"concentration\": 0.71, \"aqi\": 1}, \"PM2.5\": {\"concentration\": 2.3, \"aqi\": 7}, \"PM10\": {\"concentration\": 2.91, \"aqi\": 2}, \"overall_aqi\": 110}",
    "Ulan Bator": "{\"CO\": {\"concentration\": 403.88, \"aqi\": 4}, \"NO2\": {\"concentration\": 27.08, \"aqi\": 33}, \"O3\": {\"concentration\": 12.7, \"aqi\": 10}, \"SO2\": {\"concentration\": 32.9, \"aqi\": 48}, \"PM2.5\": {\"concentration\": 18.12, \"aqi\": 55}, \"PM10\": {\"concentration\": 19.25, \"aqi\": 17}, \"overall_aqi\": 55}",
    "Podgorica": "{\"CO\": {\"concentration\": 208.62, \"aqi\": 2}, \"NO2\": {\"concentration\": 2.04, \"aqi\": 2}, \"O3\": {\"concentration\": 77.25, \"aqi\": 105}, \"SO2\": {\"concentration\": 1.13, \"aqi\": 1}, \"PM2.5\": {\"concentration\": 8.81, \"aqi\": 28}, \"PM10\": {\"concentration\": 15.87, \"aqi\": 14}, \"overall_aqi\": 105}",
    "Plymouth": "{\"CO\": {\"concentration\": 223.64, \"aqi\": 2}, \"NO2\": {\"concentration\": 1.74, \"aqi\": 2}, \"O3\": {\"concentration\": 70.81, \"aqi\": 86}, \"SO2\": {\"concentration\": 1.19, \"aqi\": 1}, \"PM2.5\": {\"concentration\": 0.75, \"aqi\": 2}, \"PM10\": {\"concentration\": 1.08, \"aqi\": 1}, \"overall_aqi\": 86}",
    "Rabat": "{\"CO\": {\"concentration\": 213.62, \"aqi\": 2}, \"NO2\": {\"concentration\": 0.15, \"aqi\": 0}, \"O3\": {\"concentration\": 97.28, \"aqi\": 155}, \"SO2\": {\"concentration\": 0.29, \"aqi\": 0}, \"PM2.5\": {\"concentration\": 1.6, \"aqi\": 5}, \"PM10\": {\"concentration\": 4.58, \"aqi\": 4}, \"overall_aqi\": 155}",
    "Maputo": "{\"CO\": {\"concentration\": 313.76, \"aqi\": 3}, \"NO2\": {\"concentration\": 0.85, \"aqi\": 1}, \"O3\": {\"concentration\": 65.8, \"aqi\": 71}, \"SO2\": {\"concentration\": 0.94, \"aqi\": 1}, \"PM2.5\": {\"concentration\": 10.15, \"aqi\": 32}, \"PM10\": {\"concentration\": 39.17, \"aqi\": 36}, \"overall_aqi\": 71}",
    "Rangoon (Yangon)": "{\"CO\": {\"concentration\": 1375.2, \"aqi\": 15}, \"NO2\": {\"concentration\": 15.42, \"aqi\": 19}, \"O3\": {\"concentration\": 2.57, \"aqi\": 2}, \"SO2\": {\"concentration\": 4.71, \"aqi\": 6}, \"PM2.5\": {\"concentration\": 51.28, \"aqi\": 121}, \"PM10\": {\"concentration\": 81.15, \"aqi\": 63}, \"overall_aqi\": 121}",
    "Windhoek": "{\"CO\": {\"concentration\": 554.09, \"aqi\": 6}, \"NO2\": {\"concentration\": 0.61, \"aqi\": 0}, \"O3\": {\"concentration\": 124.45, \"aqi\": 203}, \"SO2\": {\"concentration\": 0.48, \"aqi\": 0}, \"PM2.5\": {\"concentration\": 34.79, \"aqi\": 88}, \"PM10\": {\"concentration\": 40.48, \"aqi\": 37}, \"overall_aqi\": 203}",
    "Yaren": "{\"CO\": {\"concentration\": 178.58, \"aqi\": 2}, \"NO2\": {\"concentration\": 0.02, \"aqi\": 0}, \"O3\": {\"concentration\": 9.48, \"aqi\": 8}, \"SO2\": {\"concentration\": 0.02, \"aqi\": 0}, \"PM2.5\": {\"concentration\": 0.5, \"aqi\": 1}, \"PM10\": {\"concentration\": 1, \"aqi\": 0}, \"overall_aqi\": 8}",
    "Kathmandu": "{\"CO\": {\"concentration\": 894.55, \"aqi\": 10}, \"NO2\": {\"concentration\": 12, \"aqi\": 15}, \"O3\": {\"concentration\": 52.21, \"aqi\": 44}, \"SO2\": {\"concentration\": 6.08, \"aqi\": 8}, \"PM2.5\": {\"concentration\": 38.05, \"aqi\": 95}, \"PM10\": {\"concentration\": 47.14, \"aqi\": 43}, \"overall_aqi\": 95}",
    "Amsterdam": "{\"CO\": {\"concentration\": 250.34, \"aqi\": 2}, \"NO2\": {\"concentration\": 26.39, \"aqi\": 32}, \"O3\": {\"concentration\": 38.62, \"aqi\": 32}, \"SO2\": {\"concentration\": 2.5, \"aqi\": 3}, \"PM2.5\": {\"concentration\": 1.46, \"aqi\": 4}, \"PM10\": {\"concentration\": 2.2, \"aqi\": 2}, \"overall_aqi\": 32}",
    "Willemstad": "{\"CO\": {\"concentration\": 220.3, \"aqi\": 2}, \"NO2\": {\"concentration\": 1.84, \"aqi\": 2}, \"O3\": {\"concentration\": 37.19, \"aqi\": 31}, \"SO2\": {\"concentration\": 5.19, \"aqi\": 7}, \"PM2.5\": {\"concentration\": 2.52, \"aqi\": 8}, \"PM10\": {\"concentration\": 7.62, \"aqi\": 7}, \"overall_aqi\": 31}",
    "Noum": "{\"CO\": {\"concentration\": 161.89, \"aqi\": 1}, \"NO2\": {\"concentration\": 0.05, \"aqi\": 0}, \"O3\": {\"concentration\": 81.54, \"aqi\": 116}, \"SO2\": {\"concentration\": 0.09, \"aqi\": 0}, \"PM2.5\": {\"concentration\": 73.5, \"aqi\": 154}, \"PM10\": {\"concentration\": 410.07, \"aqi\": 280}, \"overall_aqi\": 280}",
    "Wellington": "{\"CO\": {\"concentration\": 226.97, \"aqi\": 2}, \"NO2\": {\"concentration\": 0.25, \"aqi\": 0}, \"O3\": {\"concentration\": 57.94, \"aqi\": 49}, \"SO2\": {\"concentration\": 0.13, \"aqi\": 0}, \"PM2.5\": {\"concentration\": 4.52, \"aqi\": 14}, \"PM10\": {\"concentration\": 11.06, \"aqi\": 10}, \"overall_aqi\": 49}",
    "Managua": "{\"CO\": {\"concentration\": 310.42, \"aqi\": 3}, \"NO2\": {\"concentration\": 3.13, \"aqi\": 3}, \"O3\": {\"concentration\": 37.55, \"aqi\": 31}, \"SO2\": {\"concentration\": 4.77, \"aqi\": 7}, \"PM2.5\": {\"concentration\": 1.65, \"aqi\": 5}, \"PM10\": {\"concentration\": 3.08, \"aqi\": 2}, \"overall_aqi\": 31}",
    "Niamey": "{\"CO\": {\"concentration\": 480.65, \"aqi\": 5}, \"NO2\": {\"concentration\": 1.37, \"aqi\": 1}, \"O3\": {\"concentration\": 42.2, \"aqi\": 35}, \"SO2\": {\"concentration\": 1.97, \"aqi\": 2}, \"PM2.5\": {\"concentration\": 9.53, \"aqi\": 30}, \"PM10\": {\"concentration\": 20.54, \"aqi\": 19}, \"overall_aqi\": 35}",
    "Abuja": "{\"CO\": {\"concentration\": 867.84, \"aqi\": 9}, \"NO2\": {\"concentration\": 3.47, \"aqi\": 4}, \"O3\": {\"concentration\": 67.23, \"aqi\": 75}, \"SO2\": {\"concentration\": 0.31, \"aqi\": 0}, \"PM2.5\": {\"concentration\": 20.58, \"aqi\": 60}, \"PM10\": {\"concentration\": 22.29, \"aqi\": 20}, \"overall_aqi\": 75}",
    "Alofi": "{\"CO\": {\"concentration\": 236.99, \"aqi\": 2}, \"NO2\": {\"concentration\": 0.09, \"aqi\": 0}, \"O3\": {\"concentration\": 82.97, \"aqi\": 119}, \"SO2\": {\"concentration\": 0.23, \"aqi\": 0}, \"PM2.5\": {\"concentration\": 3.45, \"aqi\": 11}, \"PM10\": {\"concentration\": 20.34, \"aqi\": 18}, \"overall_aqi\": 119}",
    "Pyongyang": "{\"CO\": {\"concentration\": 333.79, \"aqi\": 3}, \"NO2\": {\"concentration\": 7.03, \"aqi\": 8}, \"O3\": {\"concentration\": 47.21, \"aqi\": 40}, \"SO2\": {\"concentration\": 4.53, \"aqi\": 6}, \"PM2.5\": {\"concentration\": 11.48, \"aqi\": 37}, \"PM10\": {\"concentration\": 19.99, \"aqi\": 18}, \"overall_aqi\": 40}",
    "Belfast": "{\"CO\": {\"concentration\": 220.3, \"aqi\": 2}, \"NO2\": {\"concentration\": 2.19, \"aqi\": 2}, \"O3\": {\"concentration\": 52.21, \"aqi\": 44}, \"SO2\": {\"concentration\": 0.53, \"aqi\": 0}, \"PM2.5\": {\"concentration\": 0.5, \"aqi\": 1}, \"PM10\": {\"concentration\": 0.6, \"aqi\": 0}, \"overall_aqi\": 44}",
    "Garapan": "{\"CO\": {\"concentration\": 148.54, \"aqi\": 1}, \"NO2\": {\"concentration\": 0.1, \"aqi\": 0}, \"O3\": {\"concentration\": 32.54, \"aqi\": 27}, \"SO2\": {\"concentration\": 0.1, \"aqi\": 0}, \"PM2.5\": {\"concentration\": 2.03, \"aqi\": 6}, \"PM10\": {\"concentration\": 4.52, \"aqi\": 4}, \"overall_aqi\": 27}",
    "Oslo": "{\"CO\": {\"concentration\": 226.97, \"aqi\": 2}, \"NO2\": {\"concentration\": 8.23, \"aqi\": 10}, \"O3\": {\"concentration\": 75.1, \"aqi\": 100}, \"SO2\": {\"concentration\": 4.47, \"aqi\": 6}, \"PM2.5\": {\"concentration\": 6.15, \"aqi\": 19}, \"PM10\": {\"concentration\": 7.87, \"aqi\": 7}, \"overall_aqi\": 100}",
    "Masqat": "{\"CO\": {\"concentration\": 453.95, \"aqi\": 5}, \"NO2\": {\"concentration\": 57.58, \"aqi\": 71}, \"O3\": {\"concentration\": 97.28, \"aqi\": 155}, \"SO2\": {\"concentration\": 34.33, \"aqi\": 50}, \"PM2.5\": {\"concentration\": 73.86, \"aqi\": 154}, \"PM10\": {\"concentration\": 159.45, \"aqi\": 102}, \"overall_aqi\": 155}",
    "Islamabad": "{\"CO\": {\"concentration\": 4005.43, \"aqi\": 45}, \"NO2\": {\"concentration\": 208.38, \"aqi\": 200}, \"O3\": {\"concentration\": 0.03, \"aqi\": 0}, \"SO2\": {\"concentration\": 16.45, \"aqi\": 24}, \"PM2.5\": {\"concentration\": 138.64, \"aqi\": 193}, \"PM10\": {\"concentration\": 163.66, \"aqi\": 104}, \"overall_aqi\": 200}",
    "Koror": "{\"CO\": {\"concentration\": 210.29, \"aqi\": 2}, \"NO2\": {\"concentration\": 0.09, \"aqi\": 0}, \"O3\": {\"concentration\": 28.61, \"aqi\": 24}, \"SO2\": {\"concentration\": 0.09, \"aqi\": 0}, \"PM2.5\": {\"concentration\": 1.31, \"aqi\": 4}, \"PM10\": {\"concentration\": 2.41, \"aqi\": 2}, \"overall_aqi\": 24}",
    "Gaza": "{\"CO\": {\"concentration\": 213.62, \"aqi\": 2}, \"NO2\": {\"concentration\": 0.38, \"aqi\": 0}, \"O3\": {\"concentration\": 105.86, \"aqi\": 177}, \"SO2\": {\"concentration\": 0.44, \"aqi\": 0}, \"PM2.5\": {\"concentration\": 16.37, \"aqi\": 51}, \"PM10\": {\"concentration\": 24.88, \"aqi\": 23}, \"overall_aqi\": 177}",
    "Ciudad de Panam\u00e1": "{\"CO\": {\"concentration\": 480.65, \"aqi\": 5}, \"NO2\": {\"concentration\": 13.71, \"aqi\": 17}, \"O3\": {\"concentration\": 8.76, \"aqi\": 7}, \"SO2\": {\"concentration\": 17.41, \"aqi\": 25}, \"PM2.5\": {\"concentration\": 3.24, \"aqi\": 10}, \"PM10\": {\"concentration\": 4.28, \"aqi\": 3}, \"overall_aqi\": 25}",
    "Port Moresby": "{\"CO\": {\"concentration\": 208.62, \"aqi\": 2}, \"NO2\": {\"concentration\": 3.38, \"aqi\": 4}, \"O3\": {\"concentration\": 37.19, \"aqi\": 31}, \"SO2\": {\"concentration\": 3.16, \"aqi\": 4}, \"PM2.5\": {\"concentration\": 5.69, \"aqi\": 18}, \"PM10\": {\"concentration\": 14.16, \"aqi\": 13}, \"overall_aqi\": 31}",
    "Asunci\u00f3n": "{\"CO\": {\"concentration\": 407.22, \"aqi\": 4}, \"NO2\": {\"concentration\": 0.34, \"aqi\": 0}, \"O3\": {\"concentration\": 35.76, \"aqi\": 30}, \"SO2\": {\"concentration\": 0.21, \"aqi\": 0}, \"PM2.5\": {\"concentration\": 11.19, \"aqi\": 36}, \"PM10\": {\"concentration\": 16.09, \"aqi\": 14}, \"overall_aqi\": 36}",
    "Lima": "{\"CO\": {\"concentration\": 727.65, \"aqi\": 8}, \"NO2\": {\"concentration\": 29.47, \"aqi\": 36}, \"O3\": {\"concentration\": 28.25, \"aqi\": 23}, \"SO2\": {\"concentration\": 20.5, \"aqi\": 30}, \"PM2.5\": {\"concentration\": 18.92, \"aqi\": 57}, \"PM10\": {\"concentration\": 32.24, \"aqi\": 29}, \"overall_aqi\": 57}",
    "Manila": "{\"CO\": {\"concentration\": 947.95, \"aqi\": 10}, \"NO2\": {\"concentration\": 20.22, \"aqi\": 25}, \"O3\": {\"concentration\": 50.78, \"aqi\": 43}, \"SO2\": {\"concentration\": 12.04, \"aqi\": 17}, \"PM2.5\": {\"concentration\": 57.57, \"aqi\": 134}, \"PM10\": {\"concentration\": 74.37, \"aqi\": 60}, \"overall_aqi\": 134}",
    "Adamstown": "{\"CO\": {\"concentration\": 171.9, \"aqi\": 1}, \"NO2\": {\"concentration\": 0.02, \"aqi\": 0}, \"O3\": {\"concentration\": 42.92, \"aqi\": 36}, \"SO2\": {\"concentration\": 0.11, \"aqi\": 0}, \"PM2.5\": {\"concentration\": 4.5, \"aqi\": 14}, \"PM10\": {\"concentration\": 9, \"aqi\": 8}, \"overall_aqi\": 36}",
    "Warszawa": "{\"CO\": {\"concentration\": 247, \"aqi\": 2}, \"NO2\": {\"concentration\": 7.54, \"aqi\": 9}, \"O3\": {\"concentration\": 101.57, \"aqi\": 166}, \"SO2\": {\"concentration\": 8.82, \"aqi\": 12}, \"PM2.5\": {\"concentration\": 10.43, \"aqi\": 33}, \"PM10\": {\"concentration\": 11.98, \"aqi\": 11}, \"overall_aqi\": 166}",
    "Lisboa": "{\"CO\": {\"concentration\": 220.3, \"aqi\": 2}, \"NO2\": {\"concentration\": 2.01, \"aqi\": 2}, \"O3\": {\"concentration\": 82.25, \"aqi\": 118}, \"SO2\": {\"concentration\": 1.25, \"aqi\": 1}, \"PM2.5\": {\"concentration\": 3.07, \"aqi\": 9}, \"PM10\": {\"concentration\": 5.97, \"aqi\": 5}, \"overall_aqi\": 118}",
    "San Juan": "{\"CO\": {\"concentration\": 243.66, \"aqi\": 2}, \"NO2\": {\"concentration\": 0.25, \"aqi\": 0}, \"O3\": {\"concentration\": 28.25, \"aqi\": 23}, \"SO2\": {\"concentration\": 0.44, \"aqi\": 0}, \"PM2.5\": {\"concentration\": 2.1, \"aqi\": 6}, \"PM10\": {\"concentration\": 3.38, \"aqi\": 3}, \"overall_aqi\": 23}",
    "Doha": "{\"CO\": {\"concentration\": 273.71, \"aqi\": 3}, \"NO2\": {\"concentration\": 26.39, \"aqi\": 32}, \"O3\": {\"concentration\": 134.47, \"aqi\": 207}, \"SO2\": {\"concentration\": 24.32, \"aqi\": 35}, \"PM2.5\": {\"concentration\": 40.74, \"aqi\": 100}, \"PM10\": {\"concentration\": 80.14, \"aqi\": 63}, \"overall_aqi\": 207}",
    "Saint-Denis": "{\"CO\": {\"concentration\": 263.69, \"aqi\": 2}, \"NO2\": {\"concentration\": 10.54, \"aqi\": 13}, \"O3\": {\"concentration\": 47.92, \"aqi\": 40}, \"SO2\": {\"concentration\": 1.86, \"aqi\": 2}, \"PM2.5\": {\"concentration\": 2.55, \"aqi\": 8}, \"PM10\": {\"concentration\": 3.5, \"aqi\": 3}, \"overall_aqi\": 40}",
    "Bucuresti": "{\"CO\": {\"concentration\": 383.85, \"aqi\": 4}, \"NO2\": {\"concentration\": 27.42, \"aqi\": 34}, \"O3\": {\"concentration\": 55.79, \"aqi\": 47}, \"SO2\": {\"concentration\": 3.4, \"aqi\": 5}, \"PM2.5\": {\"concentration\": 17.15, \"aqi\": 53}, \"PM10\": {\"concentration\": 21.99, \"aqi\": 20}, \"overall_aqi\": 53}",
    "Moscow": "{\"CO\": {\"concentration\": 297.07, \"aqi\": 3}, \"NO2\": {\"concentration\": 41.13, \"aqi\": 51}, \"O3\": {\"concentration\": 27.9, \"aqi\": 23}, \"SO2\": {\"concentration\": 23.37, \"aqi\": 34}, \"PM2.5\": {\"concentration\": 10.1, \"aqi\": 32}, \"PM10\": {\"concentration\": 11.99, \"aqi\": 11}, \"overall_aqi\": 51}",
    "Kigali": "{\"CO\": {\"concentration\": 363.83, \"aqi\": 4}, \"NO2\": {\"concentration\": 1.67, \"aqi\": 2}, \"O3\": {\"concentration\": 32.54, \"aqi\": 27}, \"SO2\": {\"concentration\": 1.28, \"aqi\": 1}, \"PM2.5\": {\"concentration\": 4.01, \"aqi\": 13}, \"PM10\": {\"concentration\": 5.94, \"aqi\": 5}, \"overall_aqi\": 27}",
    "Jamestown": "{\"CO\": {\"concentration\": 201.94, \"aqi\": 2}, \"NO2\": {\"concentration\": 0.01, \"aqi\": 0}, \"O3\": {\"concentration\": 64.37, \"aqi\": 66}, \"SO2\": {\"concentration\": 0.25, \"aqi\": 0}, \"PM2.5\": {\"concentration\": 3.49, \"aqi\": 11}, \"PM10\": {\"concentration\": 15.67, \"aqi\": 14}, \"overall_aqi\": 66}",
    "Basseterre": "{\"CO\": {\"concentration\": 223.64, \"aqi\": 2}, \"NO2\": {\"concentration\": 0.16, \"aqi\": 0}, \"O3\": {\"concentration\": 34.33, \"aqi\": 29}, \"SO2\": {\"concentration\": 0.17, \"aqi\": 0}, \"PM2.5\": {\"concentration\": 1.21, \"aqi\": 3}, \"PM10\": {\"concentration\": 3.14, \"aqi\": 2}, \"overall_aqi\": 29}",
    "Castries": "{\"CO\": {\"concentration\": 220.3, \"aqi\": 2}, \"NO2\": {\"concentration\": 2.04, \"aqi\": 2}, \"O3\": {\"concentration\": 105.86, \"aqi\": 177}, \"SO2\": {\"concentration\": 0.75, \"aqi\": 1}, \"PM2.5\": {\"concentration\": 7.09, \"aqi\": 23}, \"PM10\": {\"concentration\": 13.78, \"aqi\": 12}, \"overall_aqi\": 177}",
    "Saint-Pierre": "{\"CO\": {\"concentration\": 220.3, \"aqi\": 2}, \"NO2\": {\"concentration\": 5.1, \"aqi\": 6}, \"O3\": {\"concentration\": 61.51, \"aqi\": 57}, \"SO2\": {\"concentration\": 0.83, \"aqi\": 1}, \"PM2.5\": {\"concentration\": 3.08, \"aqi\": 10}, \"PM10\": {\"concentration\": 3.41, \"aqi\": 3}, \"overall_aqi\": 57}",
    "Kingstown": "{\"CO\": {\"concentration\": 223.64, \"aqi\": 2}, \"NO2\": {\"concentration\": 3.3, \"aqi\": 4}, \"O3\": {\"concentration\": 33.26, \"aqi\": 28}, \"SO2\": {\"concentration\": 2.47, \"aqi\": 3}, \"PM2.5\": {\"concentration\": 2.03, \"aqi\": 6}, \"PM10\": {\"concentration\": 2.88, \"aqi\": 2}, \"overall_aqi\": 28}",
    "Apia": "{\"CO\": {\"concentration\": 201.94, \"aqi\": 2}, \"NO2\": {\"concentration\": 0.23, \"aqi\": 0}, \"O3\": {\"concentration\": 72.24, \"aqi\": 91}, \"SO2\": {\"concentration\": 0.44, \"aqi\": 0}, \"PM2.5\": {\"concentration\": 6.83, \"aqi\": 22}, \"PM10\": {\"concentration\": 11.87, \"aqi\": 10}, \"overall_aqi\": 91}",
    "San Marino": "{\"CO\": {\"concentration\": 230.31, \"aqi\": 2}, \"NO2\": {\"concentration\": 0.8, \"aqi\": 1}, \"O3\": {\"concentration\": 84.4, \"aqi\": 123}, \"SO2\": {\"concentration\": 0.23, \"aqi\": 0}, \"PM2.5\": {\"concentration\": 1.62, \"aqi\": 5}, \"PM10\": {\"concentration\": 1.91, \"aqi\": 1}, \"overall_aqi\": 123}",
    "S\u00e3o Tom\u00e9": "{\"CO\": {\"concentration\": 433.92, \"aqi\": 4}, \"NO2\": {\"concentration\": 0.15, \"aqi\": 0}, \"O3\": {\"concentration\": 31.11, \"aqi\": 26}, \"SO2\": {\"concentration\": 0.17, \"aqi\": 0}, \"PM2.5\": {\"concentration\": 2.83, \"aqi\": 9}, \"PM10\": {\"concentration\": 4.49, \"aqi\": 4}, \"overall_aqi\": 26}",
    "Riyadh": "{\"CO\": {\"concentration\": 307.08, \"aqi\": 3}, \"NO2\": {\"concentration\": 65.8, \"aqi\": 82}, \"O3\": {\"concentration\": 72.96, \"aqi\": 93}, \"SO2\": {\"concentration\": 65.8, \"aqi\": 64}, \"PM2.5\": {\"concentration\": 24.73, \"aqi\": 68}, \"PM10\": {\"concentration\": 67.71, \"aqi\": 56}, \"overall_aqi\": 93}",
    "Edinburgh": "{\"CO\": {\"concentration\": 226.97, \"aqi\": 2}, \"NO2\": {\"concentration\": 2.06, \"aqi\": 2}, \"O3\": {\"concentration\": 62.94, \"aqi\": 62}, \"SO2\": {\"concentration\": 0.82, \"aqi\": 1}, \"PM2.5\": {\"concentration\": 0.5, \"aqi\": 1}, \"PM10\": {\"concentration\": 0.63, \"aqi\": 0}, \"overall_aqi\": 62}",
    "Dakar": "{\"CO\": {\"concentration\": 208.62, \"aqi\": 2}, \"NO2\": {\"concentration\": 0.43, \"aqi\": 0}, \"O3\": {\"concentration\": 50.07, \"aqi\": 42}, \"SO2\": {\"concentration\": 0.92, \"aqi\": 1}, \"PM2.5\": {\"concentration\": 0.98, \"aqi\": 3}, \"PM10\": {\"concentration\": 2.61, \"aqi\": 2}, \"overall_aqi\": 42}",
    "Belgrade": "{\"CO\": {\"concentration\": 226.97, \"aqi\": 2}, \"NO2\": {\"concentration\": 5.83, \"aqi\": 7}, \"O3\": {\"concentration\": 90.12, \"aqi\": 137}, \"SO2\": {\"concentration\": 2.35, \"aqi\": 3}, \"PM2.5\": {\"concentration\": 12.62, \"aqi\": 40}, \"PM10\": {\"concentration\": 15.31, \"aqi\": 14}, \"overall_aqi\": 137}",
    "Freetown": "{\"CO\": {\"concentration\": 270.37, \"aqi\": 3}, \"NO2\": {\"concentration\": 0.09, \"aqi\": 0}, \"O3\": {\"concentration\": 42.92, \"aqi\": 36}, \"SO2\": {\"concentration\": 0.06, \"aqi\": 0}, \"PM2.5\": {\"concentration\": 1.91, \"aqi\": 6}, \"PM10\": {\"concentration\": 2.67, \"aqi\": 2}, \"overall_aqi\": 36}",
    "Singapore": "{\"CO\": {\"concentration\": 2937.32, \"aqi\": 33}, \"NO2\": {\"concentration\": 42.84, \"aqi\": 53}, \"O3\": {\"concentration\": 0, \"aqi\": 0}, \"SO2\": {\"concentration\": 42.44, \"aqi\": 53}, \"PM2.5\": {\"concentration\": 38.74, \"aqi\": 96}, \"PM10\": {\"concentration\": 43.72, \"aqi\": 40}, \"overall_aqi\": 96}",
    "Bratislava": "{\"CO\": {\"concentration\": 210.29, \"aqi\": 2}, \"NO2\": {\"concentration\": 1.8, \"aqi\": 2}, \"O3\": {\"concentration\": 86.55, \"aqi\": 128}, \"SO2\": {\"concentration\": 0.72, \"aqi\": 1}, \"PM2.5\": {\"concentration\": 2.66, \"aqi\": 8}, \"PM10\": {\"concentration\": 3.59, \"aqi\": 3}, \"overall_aqi\": 128}",
    "Ljubljana": "{\"CO\": {\"concentration\": 211.95, \"aqi\": 2}, \"NO2\": {\"concentration\": 2.01, \"aqi\": 2}, \"O3\": {\"concentration\": 75.1, \"aqi\": 100}, \"SO2\": {\"concentration\": 0.49, \"aqi\": 0}, \"PM2.5\": {\"concentration\": 2.01, \"aqi\": 6}, \"PM10\": {\"concentration\": 2.32, \"aqi\": 2}, \"overall_aqi\": 100}",
    "Honiara": "{\"CO\": {\"concentration\": 183.58, \"aqi\": 2}, \"NO2\": {\"concentration\": 0.68, \"aqi\": 0}, \"O3\": {\"concentration\": 15.38, \"aqi\": 13}, \"SO2\": {\"concentration\": 0.41, \"aqi\": 0}, \"PM2.5\": {\"concentration\": 5.27, \"aqi\": 17}, \"PM10\": {\"concentration\": 5.78, \"aqi\": 5}, \"overall_aqi\": 17}",
    "Mogadishu": "{\"CO\": {\"concentration\": 198.6, \"aqi\": 2}, \"NO2\": {\"concentration\": 0.08, \"aqi\": 0}, \"O3\": {\"concentration\": 31.47, \"aqi\": 26}, \"SO2\": {\"concentration\": 0.18, \"aqi\": 0}, \"PM2.5\": {\"concentration\": 3.4, \"aqi\": 11}, \"PM10\": {\"concentration\": 10.36, \"aqi\": 9}, \"overall_aqi\": 26}",
    "Pretoria": "{\"CO\": {\"concentration\": 383.85, \"aqi\": 4}, \"NO2\": {\"concentration\": 1.24, \"aqi\": 1}, \"O3\": {\"concentration\": 111.58, \"aqi\": 191}, \"SO2\": {\"concentration\": 2.24, \"aqi\": 3}, \"PM2.5\": {\"concentration\": 19.88, \"aqi\": 58}, \"PM10\": {\"concentration\": 26.9, \"aqi\": 24}, \"overall_aqi\": 191}",
    "Seoul": "{\"CO\": {\"concentration\": 2323.15, \"aqi\": 26}, \"NO2\": {\"concentration\": 100.08, \"aqi\": 111}, \"O3\": {\"concentration\": 0, \"aqi\": 0}, \"SO2\": {\"concentration\": 75.34, \"aqi\": 68}, \"PM2.5\": {\"concentration\": 52.94, \"aqi\": 125}, \"PM10\": {\"concentration\": 72.63, \"aqi\": 59}, \"overall_aqi\": 125}",
    "Juba": "{\"CO\": {\"concentration\": 247, \"aqi\": 2}, \"NO2\": {\"concentration\": 0.47, \"aqi\": 0}, \"O3\": {\"concentration\": 8.58, \"aqi\": 7}, \"SO2\": {\"concentration\": 0.07, \"aqi\": 0}, \"PM2.5\": {\"concentration\": 0.5, \"aqi\": 1}, \"PM10\": {\"concentration\": 1.25, \"aqi\": 1}, \"overall_aqi\": 7}",
    "Madrid": "{\"CO\": {\"concentration\": 200.27, \"aqi\": 2}, \"NO2\": {\"concentration\": 1.76, \"aqi\": 2}, \"O3\": {\"concentration\": 68.67, \"aqi\": 80}, \"SO2\": {\"concentration\": 0.11, \"aqi\": 0}, \"PM2.5\": {\"concentration\": 0.63, \"aqi\": 2}, \"PM10\": {\"concentration\": 0.84, \"aqi\": 0}, \"overall_aqi\": 80}",
    "Colombo, Sri Jayawardenepura Kotte": "{\"CO\": {\"concentration\": 350.48, \"aqi\": 3}, \"NO2\": {\"concentration\": 9.17, \"aqi\": 11}, \"O3\": {\"concentration\": 55.79, \"aqi\": 47}, \"SO2\": {\"concentration\": 4.89, \"aqi\": 7}, \"PM2.5\": {\"concentration\": 2.53, \"aqi\": 8}, \"PM10\": {\"concentration\": 4.89, \"aqi\": 4}, \"overall_aqi\": 47}",
    "Khartum": "{\"CO\": {\"concentration\": 223.64, \"aqi\": 2}, \"NO2\": {\"concentration\": 1.22, \"aqi\": 1}, \"O3\": {\"concentration\": 75.1, \"aqi\": 100}, \"SO2\": {\"concentration\": 0.82, \"aqi\": 1}, \"PM2.5\": {\"concentration\": 40.38, \"aqi\": 99}, \"PM10\": {\"concentration\": 190.45, \"aqi\": 118}, \"overall_aqi\": 118}",
    "Paramaribo": "{\"CO\": {\"concentration\": 323.77, \"aqi\": 3}, \"NO2\": {\"concentration\": 1.54, \"aqi\": 1}, \"O3\": {\"concentration\": 75.1, \"aqi\": 100}, \"SO2\": {\"concentration\": 3.07, \"aqi\": 4}, \"PM2.5\": {\"concentration\": 3.11, \"aqi\": 10}, \"PM10\": {\"concentration\": 4.63, \"aqi\": 4}, \"overall_aqi\": 100}",
    "Longyearbyen": "{\"CO\": {\"concentration\": 240.33, \"aqi\": 2}, \"NO2\": {\"concentration\": 0.03, \"aqi\": 0}, \"O3\": {\"concentration\": 67.23, \"aqi\": 75}, \"SO2\": {\"concentration\": 0.01, \"aqi\": 0}, \"PM2.5\": {\"concentration\": 0.5, \"aqi\": 1}, \"PM10\": {\"concentration\": 0.75, \"aqi\": 0}, \"overall_aqi\": 75}",
    "Mbabane": "{\"CO\": {\"concentration\": 323.77, \"aqi\": 3}, \"NO2\": {\"concentration\": 0.7, \"aqi\": 0}, \"O3\": {\"concentration\": 87.98, \"aqi\": 132}, \"SO2\": {\"concentration\": 2.44, \"aqi\": 3}, \"PM2.5\": {\"concentration\": 13.7, \"aqi\": 44}, \"PM10\": {\"concentration\": 19.25, \"aqi\": 17}, \"overall_aqi\": 132}",
    "Stockholm": "{\"CO\": {\"concentration\": 250.34, \"aqi\": 2}, \"NO2\": {\"concentration\": 9.77, \"aqi\": 12}, \"O3\": {\"concentration\": 92.98, \"aqi\": 144}, \"SO2\": {\"concentration\": 9.3, \"aqi\": 13}, \"PM2.5\": {\"concentration\": 10.12, \"aqi\": 32}, \"PM10\": {\"concentration\": 11.98, \"aqi\": 11}, \"overall_aqi\": 144}",
    "Bern": "{\"CO\": {\"concentration\": 257.02, \"aqi\": 2}, \"NO2\": {\"concentration\": 4.5, \"aqi\": 5}, \"O3\": {\"concentration\": 82.97, \"aqi\": 119}, \"SO2\": {\"concentration\": 2, \"aqi\": 2}, \"PM2.5\": {\"concentration\": 3.57, \"aqi\": 11}, \"PM10\": {\"concentration\": 3.97, \"aqi\": 3}, \"overall_aqi\": 119}",
    "Damascus": "{\"CO\": {\"concentration\": 183.58, \"aqi\": 2}, \"NO2\": {\"concentration\": 2.31, \"aqi\": 2}, \"O3\": {\"concentration\": 140.19, \"aqi\": 209}, \"SO2\": {\"concentration\": 2.8, \"aqi\": 4}, \"PM2.5\": {\"concentration\": 17.86, \"aqi\": 54}, \"PM10\": {\"concentration\": 50.24, \"aqi\": 46}, \"overall_aqi\": 209}",
    "Dushanbe": "{\"CO\": {\"concentration\": 253.68, \"aqi\": 2}, \"NO2\": {\"concentration\": 3.64, \"aqi\": 4}, \"O3\": {\"concentration\": 65.8, \"aqi\": 71}, \"SO2\": {\"concentration\": 13.11, \"aqi\": 19}, \"PM2.5\": {\"concentration\": 9.52, \"aqi\": 30}, \"PM10\": {\"concentration\": 28.85, \"aqi\": 26}, \"overall_aqi\": 71}",
    "Dodoma": "{\"CO\": {\"concentration\": 240.33, \"aqi\": 2}, \"NO2\": {\"concentration\": 0.5, \"aqi\": 0}, \"O3\": {\"concentration\": 52.21, \"aqi\": 44}, \"SO2\": {\"concentration\": 0.23, \"aqi\": 0}, \"PM2.5\": {\"concentration\": 2.78, \"aqi\": 9}, \"PM10\": {\"concentration\": 4.24, \"aqi\": 3}, \"overall_aqi\": 44}",
    "Bangkok": "{\"CO\": {\"concentration\": 5928.04, \"aqi\": 65}, \"NO2\": {\"concentration\": 36.33, \"aqi\": 45}, \"O3\": {\"concentration\": 0, \"aqi\": 0}, \"SO2\": {\"concentration\": 74.39, \"aqi\": 68}, \"PM2.5\": {\"concentration\": 170.08, \"aqi\": 219}, \"PM10\": {\"concentration\": 232.48, \"aqi\": 139}, \"overall_aqi\": 219}",
    "Kinshasa": "{\"CO\": {\"concentration\": 574.11, \"aqi\": 6}, \"NO2\": {\"concentration\": 1.27, \"aqi\": 1}, \"O3\": {\"concentration\": 52.21, \"aqi\": 44}, \"SO2\": {\"concentration\": 0.28, \"aqi\": 0}, \"PM2.5\": {\"concentration\": 6.79, \"aqi\": 22}, \"PM10\": {\"concentration\": 14.06, \"aqi\": 13}, \"overall_aqi\": 44}",
    "Lom\u00e9": "{\"CO\": {\"concentration\": 494, \"aqi\": 5}, \"NO2\": {\"concentration\": 1.24, \"aqi\": 1}, \"O3\": {\"concentration\": 30.4, \"aqi\": 25}, \"SO2\": {\"concentration\": 0.86, \"aqi\": 1}, \"PM2.5\": {\"concentration\": 4.78, \"aqi\": 15}, \"PM10\": {\"concentration\": 11.93, \"aqi\": 11}, \"overall_aqi\": 25}",
    "Fakaofo": "{\"CO\": {\"concentration\": 206.95, \"aqi\": 2}, \"NO2\": {\"concentration\": 0.03, \"aqi\": 0}, \"O3\": {\"concentration\": 54.36, \"aqi\": 46}, \"SO2\": {\"concentration\": 0.14, \"aqi\": 0}, \"PM2.5\": {\"concentration\": 1.41, \"aqi\": 4}, \"PM10\": {\"concentration\": 3.21, \"aqi\": 2}, \"overall_aqi\": 46}",
    "Nuku'alofa": "{\"CO\": {\"concentration\": 226.97, \"aqi\": 2}, \"NO2\": {\"concentration\": 0.17, \"aqi\": 0}, \"O3\": {\"concentration\": 75.82, \"aqi\": 102}, \"SO2\": {\"concentration\": 0.54, \"aqi\": 0}, \"PM2.5\": {\"concentration\": 5.37, \"aqi\": 17}, \"PM10\": {\"concentration\": 22.42, \"aqi\": 20}, \"overall_aqi\": 102}",
    "Port-of-Spain": "{\"CO\": {\"concentration\": 233.65, \"aqi\": 2}, \"NO2\": {\"concentration\": 4.16, \"aqi\": 5}, \"O3\": {\"concentration\": 14.13, \"aqi\": 11}, \"SO2\": {\"concentration\": 1.57, \"aqi\": 2}, \"PM2.5\": {\"concentration\": 0.62, \"aqi\": 2}, \"PM10\": {\"concentration\": 1.01, \"aqi\": 0}, \"overall_aqi\": 11}",
    "Tunis": "{\"CO\": {\"concentration\": 226.97, \"aqi\": 2}, \"NO2\": {\"concentration\": 1.86, \"aqi\": 2}, \"O3\": {\"concentration\": 113.01, \"aqi\": 195}, \"SO2\": {\"concentration\": 2.44, \"aqi\": 3}, \"PM2.5\": {\"concentration\": 24.41, \"aqi\": 68}, \"PM10\": {\"concentration\": 72.7, \"aqi\": 59}, \"overall_aqi\": 195}",
    "Ankara": "{\"CO\": {\"concentration\": 634.19, \"aqi\": 7}, \"NO2\": {\"concentration\": 116.53, \"aqi\": 120}, \"O3\": {\"concentration\": 32.19, \"aqi\": 27}, \"SO2\": {\"concentration\": 24.32, \"aqi\": 35}, \"PM2.5\": {\"concentration\": 31.25, \"aqi\": 81}, \"PM10\": {\"concentration\": 34.77, \"aqi\": 32}, \"overall_aqi\": 120}",
    "Ashgabat": "{\"CO\": {\"concentration\": 226.97, \"aqi\": 2}, \"NO2\": {\"concentration\": 22.62, \"aqi\": 28}, \"O3\": {\"concentration\": 54.36, \"aqi\": 46}, \"SO2\": {\"concentration\": 12.04, \"aqi\": 17}, \"PM2.5\": {\"concentration\": 10.63, \"aqi\": 34}, \"PM10\": {\"concentration\": 51.67, \"aqi\": 47}, \"overall_aqi\": 47}",
    "Cockburn Town": "{\"CO\": {\"concentration\": 220.3, \"aqi\": 2}, \"NO2\": {\"concentration\": 0.23, \"aqi\": 0}, \"O3\": {\"concentration\": 40.41, \"aqi\": 34}, \"SO2\": {\"concentration\": 0.33, \"aqi\": 0}, \"PM2.5\": {\"concentration\": 2.34, \"aqi\": 7}, \"PM10\": {\"concentration\": 4.9, \"aqi\": 4}, \"overall_aqi\": 34}",
    "Funafuti": "{\"CO\": {\"concentration\": 210.29, \"aqi\": 2}, \"NO2\": {\"concentration\": 0.01, \"aqi\": 0}, \"O3\": {\"concentration\": 40.41, \"aqi\": 34}, \"SO2\": {\"concentration\": 0.05, \"aqi\": 0}, \"PM2.5\": {\"concentration\": 0.53, \"aqi\": 1}, \"PM10\": {\"concentration\": 1.15, \"aqi\": 1}, \"overall_aqi\": 34}",
    "Kampala": "{\"CO\": {\"concentration\": 747.68, \"aqi\": 8}, \"NO2\": {\"concentration\": 3.81, \"aqi\": 4}, \"O3\": {\"concentration\": 31.11, \"aqi\": 26}, \"SO2\": {\"concentration\": 3.4, \"aqi\": 5}, \"PM2.5\": {\"concentration\": 10.88, \"aqi\": 35}, \"PM10\": {\"concentration\": 20.89, \"aqi\": 19}, \"overall_aqi\": 35}",
    "Kyiv": "{\"CO\": {\"concentration\": 277.04, \"aqi\": 3}, \"NO2\": {\"concentration\": 14.91, \"aqi\": 18}, \"O3\": {\"concentration\": 68.67, \"aqi\": 80}, \"SO2\": {\"concentration\": 29.8, \"aqi\": 43}, \"PM2.5\": {\"concentration\": 16.13, \"aqi\": 51}, \"PM10\": {\"concentration\": 17.69, \"aqi\": 16}, \"overall_aqi\": 80}",
    "Abu Dhabi": "{\"CO\": {\"concentration\": 277.04, \"aqi\": 3}, \"NO2\": {\"concentration\": 0.14, \"aqi\": 0}, \"O3\": {\"concentration\": 133.04, \"aqi\": 206}, \"SO2\": {\"concentration\": 1.42, \"aqi\": 2}, \"PM2.5\": {\"concentration\": 44.69, \"aqi\": 108}, \"PM10\": {\"concentration\": 70.99, \"aqi\": 58}, \"overall_aqi\": 206}",
    "Washington": "{\"CO\": {\"concentration\": 534.06, \"aqi\": 6}, \"NO2\": {\"concentration\": 33.93, \"aqi\": 42}, \"O3\": {\"concentration\": 104.43, \"aqi\": 173}, \"SO2\": {\"concentration\": 5.42, \"aqi\": 7}, \"PM2.5\": {\"concentration\": 30.2, \"aqi\": 79}, \"PM10\": {\"concentration\": 34.22, \"aqi\": 31}, \"overall_aqi\": 173}",
    "Montevideo": "{\"CO\": {\"concentration\": 367.17, \"aqi\": 4}, \"NO2\": {\"concentration\": 8.65, \"aqi\": 10}, \"O3\": {\"concentration\": 25.39, \"aqi\": 21}, \"SO2\": {\"concentration\": 19.07, \"aqi\": 28}, \"PM2.5\": {\"concentration\": 4.15, \"aqi\": 13}, \"PM10\": {\"concentration\": 7.56, \"aqi\": 7}, \"overall_aqi\": 28}",
    "Toskent": "{\"CO\": {\"concentration\": 208.62, \"aqi\": 2}, \"NO2\": {\"concentration\": 7.54, \"aqi\": 9}, \"O3\": {\"concentration\": 56.51, \"aqi\": 47}, \"SO2\": {\"concentration\": 1.01, \"aqi\": 1}, \"PM2.5\": {\"concentration\": 7.44, \"aqi\": 24}, \"PM10\": {\"concentration\": 33.71, \"aqi\": 31}, \"overall_aqi\": 47}",
    "Port-Vila": "{\"CO\": {\"concentration\": 213.62, \"aqi\": 2}, \"NO2\": {\"concentration\": 0.21, \"aqi\": 0}, \"O3\": {\"concentration\": 49.35, \"aqi\": 41}, \"SO2\": {\"concentration\": 0.22, \"aqi\": 0}, \"PM2.5\": {\"concentration\": 4.46, \"aqi\": 14}, \"PM10\": {\"concentration\": 13.12, \"aqi\": 12}, \"overall_aqi\": 41}",
    "Caracas": "{\"CO\": {\"concentration\": 400.54, \"aqi\": 4}, \"NO2\": {\"concentration\": 31.19, \"aqi\": 38}, \"O3\": {\"concentration\": 42.2, \"aqi\": 35}, \"SO2\": {\"concentration\": 80.11, \"aqi\": 70}, \"PM2.5\": {\"concentration\": 16, \"aqi\": 51}, \"PM10\": {\"concentration\": 19.18, \"aqi\": 17}, \"overall_aqi\": 70}",
    "Hanoi": "{\"CO\": {\"concentration\": 1361.85, \"aqi\": 15}, \"NO2\": {\"concentration\": 58.95, \"aqi\": 73}, \"O3\": {\"concentration\": 0.29, \"aqi\": 0}, \"SO2\": {\"concentration\": 41.49, \"aqi\": 53}, \"PM2.5\": {\"concentration\": 56.3, \"aqi\": 131}, \"PM10\": {\"concentration\": 75.31, \"aqi\": 60}, \"overall_aqi\": 131}",
    "Road Town": "{\"CO\": {\"concentration\": 236.99, \"aqi\": 2}, \"NO2\": {\"concentration\": 0.1, \"aqi\": 0}, \"O3\": {\"concentration\": 28.97, \"aqi\": 24}, \"SO2\": {\"concentration\": 0.24, \"aqi\": 0}, \"PM2.5\": {\"concentration\": 2.25, \"aqi\": 7}, \"PM10\": {\"concentration\": 5.71, \"aqi\": 5}, \"overall_aqi\": 24}",
    "Charlotte Amalie": "{\"CO\": {\"concentration\": 236.99, \"aqi\": 2}, \"NO2\": {\"concentration\": 0.16, \"aqi\": 0}, \"O3\": {\"concentration\": 29.68, \"aqi\": 25}, \"SO2\": {\"concentration\": 0.26, \"aqi\": 0}, \"PM2.5\": {\"concentration\": 2.37, \"aqi\": 7}, \"PM10\": {\"concentration\": 5.72, \"aqi\": 5}, \"overall_aqi\": 25}",
    "Cardiff": "{\"CO\": {\"concentration\": 230.31, \"aqi\": 2}, \"NO2\": {\"concentration\": 3.43, \"aqi\": 4}, \"O3\": {\"concentration\": 70.81, \"aqi\": 86}, \"SO2\": {\"concentration\": 1.4, \"aqi\": 2}, \"PM2.5\": {\"concentration\": 0.55, \"aqi\": 1}, \"PM10\": {\"concentration\": 0.72, \"aqi\": 0}, \"overall_aqi\": 86}",
    "Mata-Utu": "{\"CO\": {\"concentration\": 203.61, \"aqi\": 2}, \"NO2\": {\"concentration\": 0.04, \"aqi\": 0}, \"O3\": {\"concentration\": 67.23, \"aqi\": 75}, \"SO2\": {\"concentration\": 0.33, \"aqi\": 0}, \"PM2.5\": {\"concentration\": 6.52, \"aqi\": 21}, \"PM10\": {\"concentration\": 14.56, \"aqi\": 13}, \"overall_aqi\": 75}",
    "Sanaa": "{\"CO\": {\"concentration\": 148.54, \"aqi\": 1}, \"NO2\": {\"concentration\": 1.74, \"aqi\": 2}, \"O3\": {\"concentration\": 118.73, \"aqi\": 201}, \"SO2\": {\"concentration\": 3.34, \"aqi\": 4}, \"PM2.5\": {\"concentration\": 24.02, \"aqi\": 67}, \"PM10\": {\"concentration\": 82.46, \"aqi\": 64}, \"overall_aqi\": 201}",
    "Lusaka": "{\"CO\": {\"concentration\": 794.41, \"aqi\": 9}, \"NO2\": {\"concentration\": 3.47, \"aqi\": 4}, \"O3\": {\"concentration\": 134.47, \"aqi\": 207}, \"SO2\": {\"concentration\": 3.73, \"aqi\": 5}, \"PM2.5\": {\"concentration\": 23.56, \"aqi\": 66}, \"PM10\": {\"concentration\": 30.69, \"aqi\": 28}, \"overall_aqi\": 207}",
    "Harare": "{\"CO\": {\"concentration\": 473.98, \"aqi\": 5}, \"NO2\": {\"concentration\": 6.08, \"aqi\": 7}, \"O3\": {\"concentration\": 133.04, \"aqi\": 206}, \"SO2\": {\"concentration\": 7.15, \"aqi\": 10}, \"PM2.5\": {\"concentration\": 26.77, \"aqi\": 72}, \"PM10\": {\"concentration\": 32.88, \"aqi\": 30}, \"overall_aqi\": 206}"
}